{
  "timestamp": "2026-06-02T21:58:58.947476+00:00",
  "timeframe": "4h",
  "market_state": [
    {
      "ticker": "GOOGL",
      "name": "Google",
      "current_date": "2026-06-02 12:00",
      "current_price": 361.8399963378906,
      "current_percentile": 0.796812749003984,
      "percentile_cohort": "extreme_low",
      "zone_label": "\u22645th percentile (Extreme Low)",
      "in_entry_zone": true,
      "regime": "mean_reversion",
      "is_mean_reverter": true,
      "is_momentum": false,
      "volatility_level": "Medium",
      "live_expectancy": {
        "expected_win_rate": 0.7256179602887379,
        "expected_return_pct": 3.1,
        "expected_holding_days": 4.0,
        "expected_return_per_day_pct": 0.775,
        "risk_adjusted_expectancy_pct": 2.066666666666667,
        "sample_size": 18
      },
      "data_source": "4h",
      "prev_midday_percentile": 7.5396825396825395,
      "change_since_prev_midday": -6.742869790678555,
      "prev_midday_price": 376.3699951171875,
      "price_change_pct": -3.8605624698570296,
      "macdv_daily": 53.13,
      "macdv_daily_trend": "Bullish",
      "macdv_delta_1d": -25.77,
      "macdv_delta_5d": -14.83,
      "macdv_delta_10d": -14.79,
      "macdv_trend": "\u2198\u2198",
      "macdv_trend_label": "CRASH",
      "days_in_zone": 3,
      "next_threshold": 50,
      "next_threshold_distance": 3.1,
      "signal_crossover": null,
      "macdv_decay_accel": -10.06,
      "transition_type": "breakdown_risk",
      "transition_score": 100,
      "macdv_zone": "strong_bullish",
      "macdv_zone_display": "Strong Bullish (+50 to +100)",
      "macdv_categorical_percentile": 77.63,
      "macdv_asymmetric_percentile": 75.0,
      "macdv_interpretation": "\ud83d\udcc8 Strengthening - within Strong Bullish"
    },
    {
      "ticker": "BTCUSD",
      "name": "Bitcoin USD",
      "current_date": "2026-06-02 20:00",
      "current_price": 67503.453125,
      "current_percentile": 1.9920318725099602,
      "percentile_cohort": "extreme_low",
      "zone_label": "\u22645th percentile (Extreme Low)",
      "in_entry_zone": true,
      "regime": "momentum",
      "is_mean_reverter": false,
      "is_momentum": true,
      "volatility_level": "High",
      "live_expectancy": {
        "expected_win_rate": 0.4948453608247423,
        "expected_return_pct": -0.22195248037749526,
        "expected_holding_days": 0.9828178694158076,
        "expected_return_per_day_pct": -0.22583276849598294,
        "risk_adjusted_expectancy_pct": -0.11097624018874763,
        "sample_size": 97
      },
      "data_source": "4h",
      "prev_midday_percentile": 7.142857142857142,
      "change_since_prev_midday": -5.150825270347182,
      "prev_midday_price": 71319.7734375,
      "price_change_pct": -5.350998928571155,
      "macdv_daily": -90.52,
      "macdv_daily_trend": "Bearish",
      "macdv_delta_1d": -20.07,
      "macdv_delta_5d": -10.47,
      "macdv_delta_10d": -8.48,
      "macdv_trend": "\u2198\u2198",
      "macdv_trend_label": "CRASH",
      "days_in_zone": 4,
      "next_threshold": -100,
      "next_threshold_distance": 9.5,
      "signal_crossover": null,
      "macdv_decay_accel": -9.4,
      "transition_type": "bearish_stable",
      "transition_score": 0,
      "macdv_zone": "extreme_bearish",
      "macdv_zone_display": "Extreme Bearish (<-100)",
      "macdv_categorical_percentile": 31.25,
      "macdv_asymmetric_percentile": 10.0,
      "macdv_interpretation": "\u2198\ufe0f Weakening - within Extreme Bearish"
    },
    {
      "ticker": "NFLX",
      "name": "Netflix Inc.",
      "current_date": "2026-06-02 12:00",
      "current_price": 83.31999969482422,
      "current_percentile": 9.56175298804781,
      "percentile_cohort": "low",
      "zone_label": "5-15th percentile (Low)",
      "in_entry_zone": true,
      "regime": "momentum",
      "is_mean_reverter": false,
      "is_momentum": true,
      "volatility_level": "High",
      "live_expectancy": {
        "expected_win_rate": 0.6096666683811008,
        "expected_return_pct": 1.15,
        "expected_holding_days": 4.0,
        "expected_return_per_day_pct": 0.2875,
        "risk_adjusted_expectancy_pct": 0.575,
        "sample_size": 118
      },
      "data_source": "4h",
      "prev_midday_percentile": 47.22222222222222,
      "change_since_prev_midday": -37.660469234174414,
      "prev_midday_price": 85.8499984741211,
      "price_change_pct": -2.9469992128881937,
      "macdv_daily": -90.23,
      "macdv_daily_trend": "Bearish",
      "macdv_delta_1d": -7.22,
      "macdv_delta_5d": -3.22,
      "macdv_delta_10d": -0.49,
      "macdv_trend": "\u2198",
      "macdv_trend_label": "DECEL",
      "days_in_zone": 15,
      "next_threshold": -100,
      "next_threshold_distance": 9.8,
      "signal_crossover": null,
      "macdv_decay_accel": -5.18,
      "transition_type": "bearish_exhaustion",
      "transition_score": 37,
      "macdv_zone": "extreme_bearish",
      "macdv_zone_display": "Extreme Bearish (<-100)",
      "macdv_categorical_percentile": 2.63,
      "macdv_asymmetric_percentile": 10.0,
      "macdv_interpretation": "\u26a0\ufe0f Extreme weakness - near bottom of Extreme Bearish"
    },
    {
      "ticker": "AMZN",
      "name": "Amazon.com Inc.",
      "current_date": "2026-06-02 12:00",
      "current_price": 256.5,
      "current_percentile": 11.952191235059761,
      "percentile_cohort": "low",
      "zone_label": "5-15th percentile (Low)",
      "in_entry_zone": true,
      "regime": "mean_reversion",
      "is_mean_reverter": true,
      "is_momentum": false,
      "volatility_level": "Medium",
      "live_expectancy": {
        "expected_win_rate": 0.37037037037037035,
        "expected_return_pct": -1.2520446074605558,
        "expected_holding_days": 2.8765432098765435,
        "expected_return_per_day_pct": -0.4352601425077468,
        "risk_adjusted_expectancy_pct": -0.8346964049737039,
        "sample_size": 27
      },
      "data_source": "4h",
      "prev_midday_percentile": 6.349206349206349,
      "change_since_prev_midday": 5.602984885853412,
      "prev_midday_price": 261.260009765625,
      "price_change_pct": -1.8219434998472135,
      "macdv_daily": 46.71,
      "macdv_daily_trend": "Neutral",
      "macdv_delta_1d": -15.95,
      "macdv_delta_5d": -6.04,
      "macdv_delta_10d": -7.18,
      "macdv_trend": "\u2198\u2198",
      "macdv_trend_label": "CRASH",
      "days_in_zone": 1,
      "next_threshold": 50,
      "next_threshold_distance": -3.3,
      "signal_crossover": null,
      "macdv_decay_accel": -0.71,
      "transition_type": "stable_ranging",
      "transition_score": 0,
      "macdv_zone": "ranging",
      "macdv_zone_display": "Ranging (-50 to +50)",
      "macdv_categorical_percentile": 79.2,
      "macdv_asymmetric_percentile": 75.0,
      "macdv_interpretation": "\u27a1\ufe0f Mid-range - within Range"
    },
    {
      "ticker": "IGLS",
      "name": "IGLS (London)",
      "current_date": "2026-06-02 16:00",
      "current_price": 126.9000015258789,
      "current_percentile": 13.147410358565736,
      "percentile_cohort": "low",
      "zone_label": "5-15th percentile (Low)",
      "in_entry_zone": true,
      "regime": "mean_reversion",
      "is_mean_reverter": true,
      "is_momentum": false,
      "volatility_level": "Medium",
      "live_expectancy": {
        "expected_win_rate": 0.6666666666666666,
        "expected_return_pct": 0.024005102055221078,
        "expected_holding_days": 4.322916666666667,
        "expected_return_per_day_pct": 0.005552987463376442,
        "risk_adjusted_expectancy_pct": 0.016003401370147385,
        "sample_size": 48
      },
      "data_source": "4h",
      "prev_midday_percentile": 47.22222222222222,
      "change_since_prev_midday": -34.074811863656485,
      "prev_midday_price": 126.87999725341797,
      "price_change_pct": 0.015766293264479567,
      "macdv_daily": 24.83,
      "macdv_daily_trend": "Ranging",
      "macdv_delta_1d": 0.53,
      "macdv_delta_5d": 2.83,
      "macdv_delta_10d": 3.14,
      "macdv_trend": "\u2197",
      "macdv_trend_label": "STR",
      "days_in_zone": 15,
      "next_threshold": null,
      "next_threshold_distance": null,
      "signal_crossover": null,
      "macdv_decay_accel": 0.78,
      "transition_type": "pre_breakout",
      "transition_score": 52,
      "macdv_zone": null,
      "macdv_zone_display": null,
      "macdv_categorical_percentile": null,
      "macdv_asymmetric_percentile": null,
      "macdv_interpretation": null
    },
    {
      "ticker": "LLY",
      "name": "Eli Lilly and Company",
      "current_date": "2026-06-02 12:00",
      "current_price": 1064.6300048828125,
      "current_percentile": 15.53784860557769,
      "percentile_cohort": "medium_low",
      "zone_label": "15-30th percentile (Medium Low)",
      "in_entry_zone": false,
      "regime": "momentum",
      "is_mean_reverter": false,
      "is_momentum": true,
      "volatility_level": "High",
      "live_expectancy": {
        "expected_win_rate": 0.6511627906976745,
        "expected_return_pct": 0.17845984229116485,
        "expected_holding_days": 2.2054263565891463,
        "expected_return_per_day_pct": 0.08091852251515036,
        "risk_adjusted_expectancy_pct": 0.08922992114558242,
        "sample_size": 43
      },
      "data_source": "4h",
      "prev_midday_percentile": 45.63492063492063,
      "change_since_prev_midday": -30.097072029342943,
      "prev_midday_price": 1082.199951171875,
      "price_change_pct": -1.6235397414347177,
      "macdv_daily": 117.74,
      "macdv_daily_trend": "Bullish",
      "macdv_delta_1d": -5.12,
      "macdv_delta_5d": 3.0,
      "macdv_delta_10d": 5.23,
      "macdv_trend": "\u2197",
      "macdv_trend_label": "STR",
      "days_in_zone": 6,
      "next_threshold": null,
      "next_threshold_distance": null,
      "signal_crossover": null,
      "macdv_decay_accel": -0.73,
      "transition_type": "momentum_building",
      "transition_score": 24,
      "macdv_zone": "ranging",
      "macdv_zone_display": "Ranging (-50 to +50)",
      "macdv_categorical_percentile": 20.35,
      "macdv_asymmetric_percentile": 25.0,
      "macdv_interpretation": "\u27a1\ufe0f Mid-range - within Range"
    },
    {
      "ticker": "BRK-B",
      "name": "Berkshire Hathaway Inc. Class B",
      "current_date": "2026-06-02 12:00",
      "current_price": 471.6499938964844,
      "current_percentile": 22.709163346613543,
      "percentile_cohort": "medium_low",
      "zone_label": "15-30th percentile (Medium Low)",
      "in_entry_zone": false,
      "regime": "momentum",
      "is_mean_reverter": false,
      "is_momentum": true,
      "volatility_level": "Low",
      "live_expectancy": {
        "expected_win_rate": 0.7333333333333333,
        "expected_return_pct": 0.3387456945001898,
        "expected_holding_days": 1.862962962962963,
        "expected_return_per_day_pct": 0.18183168492057902,
        "risk_adjusted_expectancy_pct": 0.3387456945001898,
        "sample_size": 45
      },
      "data_source": "4h",
      "prev_midday_percentile": 3.968253968253968,
      "change_since_prev_midday": 18.740909378359575,
      "prev_midday_price": 470.2900085449219,
      "price_change_pct": 0.2891801498760939,
      "macdv_daily": -10.34,
      "macdv_daily_trend": "Neutral",
      "macdv_delta_1d": -8.19,
      "macdv_delta_5d": -8.2,
      "macdv_delta_10d": -4.05,
      "macdv_trend": "\u2198\u2198",
      "macdv_trend_label": "CRASH",
      "days_in_zone": 15,
      "next_threshold": null,
      "next_threshold_distance": null,
      "signal_crossover": null,
      "macdv_decay_accel": 4.29,
      "transition_type": "stable_ranging",
      "transition_score": 0,
      "macdv_zone": "strong_bearish",
      "macdv_zone_display": "Strong Bearish (-100 to -50)",
      "macdv_categorical_percentile": 80.85,
      "macdv_asymmetric_percentile": 25.0,
      "macdv_interpretation": "\ud83d\udd04 Strong recovery - near top of Strong Bearish"
    },
    {
      "ticker": "TSLA",
      "name": "Tesla, Inc.",
      "current_date": "2026-06-02 12:00",
      "current_price": 423.739990234375,
      "current_percentile": 24.302788844621514,
      "percentile_cohort": "medium_low",
      "zone_label": "15-30th percentile (Medium Low)",
      "in_entry_zone": false,
      "regime": "momentum",
      "is_mean_reverter": false,
      "is_momentum": true,
      "volatility_level": "High",
      "live_expectancy": {
        "expected_win_rate": 0.5045259903667294,
        "expected_return_pct": 0.07,
        "expected_holding_days": 4.0,
        "expected_return_per_day_pct": 0.0175,
        "risk_adjusted_expectancy_pct": 0.035,
        "sample_size": 124
      },
      "data_source": "4h",
      "prev_midday_percentile": 2.7777777777777777,
      "change_since_prev_midday": 21.525011066843735,
      "prev_midday_price": 415.8800048828125,
      "price_change_pct": 1.8899647156100479,
      "macdv_daily": 60.47,
      "macdv_daily_trend": "Bullish",
      "macdv_delta_1d": -5.7,
      "macdv_delta_5d": -1.79,
      "macdv_delta_10d": -2.3,
      "macdv_trend": "\u2192",
      "macdv_trend_label": "FLAT",
      "days_in_zone": 12,
      "next_threshold": null,
      "next_threshold_distance": null,
      "signal_crossover": null,
      "macdv_decay_accel": 6.22,
      "transition_type": "peak_risk",
      "transition_score": 30,
      "macdv_zone": "ranging",
      "macdv_zone_display": "Ranging (-50 to +50)",
      "macdv_categorical_percentile": 4.76,
      "macdv_asymmetric_percentile": 50.0,
      "macdv_interpretation": "\ud83d\udca1 Oversold - near bottom of Range"
    },
    {
      "ticker": "COST",
      "name": "Costco",
      "current_date": "2026-06-02 12:00",
      "current_price": 954.239990234375,
      "current_percentile": 25.89641434262948,
      "percentile_cohort": "medium_low",
      "zone_label": "15-30th percentile (Medium Low)",
      "in_entry_zone": false,
      "regime": "mean_reversion",
      "is_mean_reverter": true,
      "is_momentum": false,
      "volatility_level": "Medium",
      "live_expectancy": {
        "expected_win_rate": 0.7575757575757576,
        "expected_return_pct": 0.6354824537342605,
        "expected_holding_days": 2.186868686868687,
        "expected_return_per_day_pct": 0.2905901289593154,
        "risk_adjusted_expectancy_pct": 0.4236549691561737,
        "sample_size": 33
      },
      "data_source": "4h",
      "prev_midday_percentile": 0.3968253968253968,
      "change_since_prev_midday": 25.499588945804085,
      "prev_midday_price": 946.1099853515625,
      "price_change_pct": 0.8593086436765058,
      "macdv_daily": -46.83,
      "macdv_daily_trend": "Neutral",
      "macdv_delta_1d": -14.84,
      "macdv_delta_5d": -19.59,
      "macdv_delta_10d": -11.52,
      "macdv_trend": "\u2198\u2198",
      "macdv_trend_label": "CRASH",
      "days_in_zone": 5,
      "next_threshold": -50,
      "next_threshold_distance": 3.2,
      "signal_crossover": null,
      "macdv_decay_accel": 8.44,
      "transition_type": "pre_breakdown",
      "transition_score": 85,
      "macdv_zone": null,
      "macdv_zone_display": null,
      "macdv_categorical_percentile": null,
      "macdv_asymmetric_percentile": null,
      "macdv_interpretation": null
    },
    {
      "ticker": "WMT",
      "name": "Walmart Inc.",
      "current_date": "2026-06-02 12:00",
      "current_price": 113.03500366210938,
      "current_percentile": 28.286852589641438,
      "percentile_cohort": "medium_low",
      "zone_label": "15-30th percentile (Medium Low)",
      "in_entry_zone": false,
      "regime": "momentum",
      "is_mean_reverter": false,
      "is_momentum": true,
      "volatility_level": "Medium",
      "live_expectancy": {
        "expected_win_rate": 0.6530612244897959,
        "expected_return_pct": 0.49599473534465666,
        "expected_holding_days": 3.370748299319729,
        "expected_return_per_day_pct": 0.1471467731496761,
        "risk_adjusted_expectancy_pct": 0.33066315689643777,
        "sample_size": 49
      },
      "data_source": "4h",
      "prev_midday_percentile": 2.380952380952381,
      "change_since_prev_midday": 25.905900208689058,
      "prev_midday_price": 114.5999984741211,
      "price_change_pct": -1.3656150373903582,
      "macdv_daily": -117.22,
      "macdv_daily_trend": "Bearish",
      "macdv_delta_1d": -17.26,
      "macdv_delta_5d": -16.91,
      "macdv_delta_10d": -17.55,
      "macdv_trend": "\u2198\u2198",
      "macdv_trend_label": "CRASH",
      "days_in_zone": 1,
      "next_threshold": null,
      "next_threshold_distance": null,
      "signal_crossover": null,
      "macdv_decay_accel": -0.76,
      "transition_type": "bearish_stable",
      "transition_score": 0,
      "macdv_zone": "strong_bullish",
      "macdv_zone_display": "Strong Bullish (+50 to +100)",
      "macdv_categorical_percentile": 95.06,
      "macdv_asymmetric_percentile": 90.0,
      "macdv_interpretation": "\ud83d\ude80 Very strong - near top of Strong Bullish"
    },
    {
      "ticker": "UNH",
      "name": "UnitedHealth Group Inc.",
      "current_date": "2026-06-02 12:00",
      "current_price": 377.94000244140625,
      "current_percentile": 34.66135458167331,
      "percentile_cohort": "medium",
      "zone_label": "30-50th percentile (Medium)",
      "in_entry_zone": false,
      "regime": "momentum",
      "is_mean_reverter": false,
      "is_momentum": true,
      "volatility_level": "High",
      "live_expectancy": {
        "expected_win_rate": 0.603448275862069,
        "expected_return_pct": -0.12374813823524121,
        "expected_holding_days": 1.7873563218390802,
        "expected_return_per_day_pct": -0.06923529277470088,
        "risk_adjusted_expectancy_pct": -0.061874069117620605,
        "sample_size": 58
      },
      "data_source": "4h",
      "prev_midday_percentile": 9.920634920634921,
      "change_since_prev_midday": 24.740719661038387,
      "prev_midday_price": 379.8599853515625,
      "price_change_pct": -0.5054448965924366,
      "macdv_daily": 101.41,
      "macdv_daily_trend": "Bullish",
      "macdv_delta_1d": -11.58,
      "macdv_delta_5d": -8.63,
      "macdv_delta_10d": -11.78,
      "macdv_trend": "\u2198\u2198",
      "macdv_trend_label": "CRASH",
      "days_in_zone": 15,
      "next_threshold": 100,
      "next_threshold_distance": 1.4,
      "signal_crossover": null,
      "macdv_decay_accel": 0.79,
      "transition_type": "breakdown_risk",
      "transition_score": 69,
      "macdv_zone": "extreme_bearish",
      "macdv_zone_display": "Extreme Bearish (<-100)",
      "macdv_categorical_percentile": 85.71,
      "macdv_asymmetric_percentile": 10.0,
      "macdv_interpretation": "\ud83d\udd04 Strong recovery - near top of Extreme Bearish"
    },
    {
      "ticker": "CSP1",
      "name": "CSP1 (LSE)",
      "current_date": "2026-06-02 16:00",
      "current_price": 60803.0,
      "current_percentile": 42.62948207171315,
      "percentile_cohort": "medium",
      "zone_label": "30-50th percentile (Medium)",
      "in_entry_zone": false,
      "regime": "mean_reversion",
      "is_mean_reverter": true,
      "is_momentum": false,
      "volatility_level": "Medium",
      "live_expectancy": {
        "expected_win_rate": 0.7391304347826086,
        "expected_return_pct": -0.11488015165084615,
        "expected_holding_days": 1.7554347826086953,
        "expected_return_per_day_pct": -0.06544256316952228,
        "risk_adjusted_expectancy_pct": -0.07658676776723077,
        "sample_size": 92
      },
      "data_source": "4h",
      "prev_midday_percentile": 49.60317460317461,
      "change_since_prev_midday": -6.9736925314614595,
      "prev_midday_price": 60685.0,
      "price_change_pct": 0.19444673313009805,
      "macdv_daily": 241.33,
      "macdv_daily_trend": "Bullish",
      "macdv_delta_1d": -0.26,
      "macdv_delta_5d": 2.04,
      "macdv_delta_10d": -0.45,
      "macdv_trend": "\u2197",
      "macdv_trend_label": "STR",
      "days_in_zone": 15,
      "next_threshold": null,
      "next_threshold_distance": null,
      "signal_crossover": null,
      "macdv_decay_accel": -0.8,
      "transition_type": "momentum_building",
      "transition_score": 16,
      "macdv_zone": null,
      "macdv_zone_display": null,
      "macdv_categorical_percentile": null,
      "macdv_asymmetric_percentile": null,
      "macdv_interpretation": null
    },
    {
      "ticker": "CNX1",
      "name": "CNX1 (LSE)",
      "current_date": "2026-06-02 16:00",
      "current_price": 130440.0,
      "current_percentile": 45.81673306772908,
      "percentile_cohort": "medium",
      "zone_label": "30-50th percentile (Medium)",
      "in_entry_zone": false,
      "regime": "mean_reversion",
      "is_mean_reverter": true,
      "is_momentum": false,
      "volatility_level": "Medium",
      "live_expectancy": {
        "expected_win_rate": 0.7291666666666666,
        "expected_return_pct": -0.11338334810696439,
        "expected_holding_days": 1.4722222222222225,
        "expected_return_per_day_pct": -0.07701510437454183,
        "risk_adjusted_expectancy_pct": -0.07558889873797627,
        "sample_size": 96
      },
      "data_source": "4h",
      "prev_midday_percentile": 57.14285714285714,
      "change_since_prev_midday": -11.326124075128057,
      "prev_midday_price": 130110.0,
      "price_change_pct": 0.2536315425409269,
      "macdv_daily": 242.02,
      "macdv_daily_trend": "Bullish",
      "macdv_delta_1d": -4.01,
      "macdv_delta_5d": -0.41,
      "macdv_delta_10d": -3.65,
      "macdv_trend": "\u2192",
      "macdv_trend_label": "FLAT",
      "days_in_zone": 15,
      "next_threshold": null,
      "next_threshold_distance": null,
      "signal_crossover": "bearish",
      "macdv_decay_accel": -5.13,
      "transition_type": "peak_risk",
      "transition_score": 56,
      "macdv_zone": null,
      "macdv_zone_display": null,
      "macdv_categorical_percentile": null,
      "macdv_asymmetric_percentile": null,
      "macdv_interpretation": null
    },
    {
      "ticker": "SPY",
      "name": "S&P 500 ETF",
      "current_date": "2026-06-02 12:00",
      "current_price": 759.469970703125,
      "current_percentile": 47.410358565737056,
      "percentile_cohort": "medium",
      "zone_label": "30-50th percentile (Medium)",
      "in_entry_zone": false,
      "regime": "mean_reversion",
      "is_mean_reverter": true,
      "is_momentum": false,
      "volatility_level": "Low",
      "live_expectancy": {
        "expected_win_rate": 0.8070175438596491,
        "expected_return_pct": 0.11250552530536415,
        "expected_holding_days": 2.839181286549708,
        "expected_return_per_day_pct": 0.039626044958223,
        "risk_adjusted_expectancy_pct": 0.11250552530536415,
        "sample_size": 57
      },
      "data_source": "4h",
      "prev_midday_percentile": 63.49206349206349,
      "change_since_prev_midday": -16.08170492632643,
      "prev_midday_price": 758.5399780273438,
      "price_change_pct": 0.12260298767637608,
      "macdv_daily": 198.25,
      "macdv_daily_trend": "Bullish",
      "macdv_delta_1d": 3.02,
      "macdv_delta_5d": 3.96,
      "macdv_delta_10d": -0.25,
      "macdv_trend": "\u2197",
      "macdv_trend_label": "STR",
      "days_in_zone": 15,
      "next_threshold": null,
      "next_threshold_distance": null,
      "signal_crossover": null,
      "macdv_decay_accel": -3.51,
      "transition_type": "momentum_building",
      "transition_score": 31,
      "macdv_zone": "ranging",
      "macdv_zone_display": "Ranging (-50 to +50)",
      "macdv_categorical_percentile": 61.54,
      "macdv_asymmetric_percentile": 50.0,
      "macdv_interpretation": "\u27a1\ufe0f Mid-range - within Range"
    },
    {
      "ticker": "VIX",
      "name": "CBOE Volatility Index",
      "current_date": "2026-06-02 12:00",
      "current_price": 15.779999732971191,
      "current_percentile": 48.20717131474104,
      "percentile_cohort": "medium",
      "zone_label": "30-50th percentile (Medium)",
      "in_entry_zone": false,
      "regime": "mean_reversion",
      "is_mean_reverter": true,
      "is_momentum": false,
      "volatility_level": "High",
      "live_expectancy": {
        "expected_win_rate": 0.6480446927374302,
        "expected_return_pct": 1.4554328477079328,
        "expected_holding_days": 0.6722532588454379,
        "expected_return_per_day_pct": 2.1650067568397775,
        "risk_adjusted_expectancy_pct": 0.7277164238539664,
        "sample_size": 179
      },
      "data_source": "4h",
      "prev_midday_percentile": 48.01587301587302,
      "change_since_prev_midday": 0.19129829886801986,
      "prev_midday_price": 16.049999237060547,
      "price_change_pct": -1.6822399808338193,
      "macdv_daily": -84.19,
      "macdv_daily_trend": "Bearish",
      "macdv_delta_1d": -1.67,
      "macdv_delta_5d": -3.76,
      "macdv_delta_10d": -2.56,
      "macdv_trend": "\u2198",
      "macdv_trend_label": "DECEL",
      "days_in_zone": 15,
      "next_threshold": null,
      "next_threshold_distance": null,
      "signal_crossover": null,
      "macdv_decay_accel": -3.69,
      "transition_type": "bearish_exhaustion",
      "transition_score": 39,
      "macdv_zone": "ranging",
      "macdv_zone_display": "Ranging (-50 to +50)",
      "macdv_categorical_percentile": 86.36,
      "macdv_asymmetric_percentile": 90.0,
      "macdv_interpretation": "\ud83d\udcc8 Strengthening - near top of Range"
    },
    {
      "ticker": "QQQ",
      "name": "Nasdaq 100 ETF",
      "current_date": "2026-06-02 12:00",
      "current_price": 746.1400146484375,
      "current_percentile": 48.60557768924303,
      "percentile_cohort": "medium",
      "zone_label": "30-50th percentile (Medium)",
      "in_entry_zone": false,
      "regime": "mean_reversion",
      "is_mean_reverter": true,
      "is_momentum": true,
      "volatility_level": "Medium",
      "live_expectancy": {
        "expected_win_rate": 0.7213114754098361,
        "expected_return_pct": 0.051622531716514965,
        "expected_holding_days": 2.2513661202185795,
        "expected_return_per_day_pct": 0.022929425495442322,
        "risk_adjusted_expectancy_pct": 0.03441502114434331,
        "sample_size": 61
      },
      "data_source": "4h",
      "prev_midday_percentile": 61.904761904761905,
      "change_since_prev_midday": -13.299184215518878,
      "prev_midday_price": 742.739990234375,
      "price_change_pct": 0.45776778667722023,
      "macdv_daily": 218.58,
      "macdv_daily_trend": "Bullish",
      "macdv_delta_1d": 7.1,
      "macdv_delta_5d": 3.43,
      "macdv_delta_10d": -0.53,
      "macdv_trend": "\u2197",
      "macdv_trend_label": "STR",
      "days_in_zone": 15,
      "next_threshold": null,
      "next_threshold_distance": null,
      "signal_crossover": null,
      "macdv_decay_accel": 3.13,
      "transition_type": "momentum_building",
      "transition_score": 27,
      "macdv_zone": "ranging",
      "macdv_zone_display": "Ranging (-50 to +50)",
      "macdv_categorical_percentile": 43.48,
      "macdv_asymmetric_percentile": 50.0,
      "macdv_interpretation": "\u27a1\ufe0f Mid-range - within Range"
    },
    {
      "ticker": "MSFT",
      "name": "Microsoft",
      "current_date": "2026-06-02 12:00",
      "current_price": 441.2900085449219,
      "current_percentile": 49.00398406374502,
      "percentile_cohort": "medium",
      "zone_label": "30-50th percentile (Medium)",
      "in_entry_zone": false,
      "regime": "mean_reversion",
      "is_mean_reverter": true,
      "is_momentum": false,
      "volatility_level": "Medium",
      "live_expectancy": {
        "expected_win_rate": 0.6849128309162449,
        "expected_return_pct": 1.17,
        "expected_holding_days": 4.0,
        "expected_return_per_day_pct": 0.2925,
        "risk_adjusted_expectancy_pct": 0.7799999999999999,
        "sample_size": 103
      },
      "data_source": "4h",
      "prev_midday_percentile": 98.4126984126984,
      "change_since_prev_midday": -49.40871434895338,
      "prev_midday_price": 460.5199890136719,
      "price_change_pct": -4.17571026828525,
      "macdv_daily": 74.82,
      "macdv_daily_trend": "Bullish",
      "macdv_delta_1d": 0.66,
      "macdv_delta_5d": 8.45,
      "macdv_delta_10d": 4.07,
      "macdv_trend": "\u2197\u2197",
      "macdv_trend_label": "ACC",
      "days_in_zone": 3,
      "next_threshold": null,
      "next_threshold_distance": null,
      "signal_crossover": null,
      "macdv_decay_accel": -22.39,
      "transition_type": "momentum_building",
      "transition_score": 67,
      "macdv_zone": "extreme_bearish",
      "macdv_zone_display": "Extreme Bearish (<-100)",
      "macdv_categorical_percentile": 16.67,
      "macdv_asymmetric_percentile": 10.0,
      "macdv_interpretation": "\u26a0\ufe0f Extreme weakness - near bottom of Extreme Bearish"
    },
    {
      "ticker": "US10",
      "name": "US 10-Year Treasury Yield",
      "current_date": "2026-06-02 12:00",
      "current_price": 4.454999923706055,
      "current_percentile": 49.40239043824701,
      "percentile_cohort": "medium",
      "zone_label": "30-50th percentile (Medium)",
      "in_entry_zone": false,
      "regime": "mean_reversion",
      "is_mean_reverter": true,
      "is_momentum": false,
      "volatility_level": "Low",
      "live_expectancy": {
        "expected_win_rate": 0.8333333333333334,
        "expected_return_pct": 0.39308798066521444,
        "expected_holding_days": 1.767094017094018,
        "expected_return_per_day_pct": 0.22244882098104024,
        "risk_adjusted_expectancy_pct": 0.39308798066521444,
        "sample_size": 78
      },
      "data_source": "4h",
      "prev_midday_percentile": 23.809523809523807,
      "change_since_prev_midday": 25.592866628723204,
      "prev_midday_price": 4.474999904632568,
      "price_change_pct": -0.4469269576030488,
      "macdv_daily": 45.19,
      "macdv_daily_trend": "Neutral",
      "macdv_delta_1d": -8.86,
      "macdv_delta_5d": -11.42,
      "macdv_delta_10d": -6.19,
      "macdv_trend": "\u2198\u2198",
      "macdv_trend_label": "CRASH",
      "days_in_zone": 1,
      "next_threshold": 50,
      "next_threshold_distance": -4.8,
      "signal_crossover": null,
      "macdv_decay_accel": -1.12,
      "transition_type": "stable_ranging",
      "transition_score": 0,
      "macdv_zone": "strong_bullish",
      "macdv_zone_display": "Strong Bullish (+50 to +100)",
      "macdv_categorical_percentile": 71.43,
      "macdv_asymmetric_percentile": 75.0,
      "macdv_interpretation": "\ud83d\udcc8 Strengthening - within Strong Bullish"
    },
    {
      "ticker": "AAPL",
      "name": "Apple",
      "current_date": "2026-06-02 12:00",
      "current_price": 315.19000244140625,
      "current_percentile": 54.18326693227091,
      "percentile_cohort": "medium_high",
      "zone_label": "50-70th percentile (Medium High)",
      "in_entry_zone": false,
      "regime": "momentum",
      "is_mean_reverter": false,
      "is_momentum": true,
      "volatility_level": "Medium-High",
      "live_expectancy": {
        "expected_win_rate": 0.43093912053202066,
        "expected_return_pct": -1.07,
        "expected_holding_days": 4.0,
        "expected_return_per_day_pct": -0.2675,
        "risk_adjusted_expectancy_pct": -0.7133333333333334,
        "sample_size": 77
      },
      "data_source": "4h",
      "prev_midday_percentile": 13.88888888888889,
      "change_since_prev_midday": 40.294378043382025,
      "prev_midday_price": 306.30999755859375,
      "price_change_pct": 2.8990254818939927,
      "macdv_daily": 163.38,
      "macdv_daily_trend": "Bullish",
      "macdv_delta_1d": -3.69,
      "macdv_delta_5d": -1.26,
      "macdv_delta_10d": 1.2,
      "macdv_trend": "\u2192",
      "macdv_trend_label": "FLAT",
      "days_in_zone": 15,
      "next_threshold": null,
      "next_threshold_distance": null,
      "signal_crossover": "bearish",
      "macdv_decay_accel": 10.02,
      "transition_type": "peak_risk",
      "transition_score": 60,
      "macdv_zone": "ranging",
      "macdv_zone_display": "Ranging (-50 to +50)",
      "macdv_categorical_percentile": 38.0,
      "macdv_asymmetric_percentile": 50.0,
      "macdv_interpretation": "\u27a1\ufe0f Mid-range - within Range"
    },
    {
      "ticker": "ES1",
      "name": "E-mini S&P 500 Futures",
      "current_date": "2026-06-02 16:00",
      "current_price": 7628.25,
      "current_percentile": 54.581673306772906,
      "percentile_cohort": "medium_high",
      "zone_label": "50-70th percentile (Medium High)",
      "in_entry_zone": false,
      "regime": "mean_reversion",
      "is_mean_reverter": true,
      "is_momentum": false,
      "volatility_level": "Medium",
      "live_expectancy": {
        "expected_win_rate": 0.6747967479674797,
        "expected_return_pct": -0.007133969269414745,
        "expected_holding_days": 0.6930894308943087,
        "expected_return_per_day_pct": -0.010292999649712774,
        "risk_adjusted_expectancy_pct": -0.004755979512943163,
        "sample_size": 246
      },
      "data_source": "4h",
      "prev_midday_percentile": 61.111111111111114,
      "change_since_prev_midday": -6.529437804338208,
      "prev_midday_price": 7613.25,
      "price_change_pct": 0.19702492365284208,
      "macdv_daily": 165.53,
      "macdv_daily_trend": "Bullish",
      "macdv_delta_1d": 0.99,
      "macdv_delta_5d": 2.38,
      "macdv_delta_10d": -0.85,
      "macdv_trend": "\u2197",
      "macdv_trend_label": "STR",
      "days_in_zone": 15,
      "next_threshold": null,
      "next_threshold_distance": null,
      "signal_crossover": null,
      "macdv_decay_accel": -3.4,
      "transition_type": "momentum_building",
      "transition_score": 19,
      "macdv_zone": "ranging",
      "macdv_zone_display": "Ranging (-50 to +50)",
      "macdv_categorical_percentile": 42.86,
      "macdv_asymmetric_percentile": 50.0,
      "macdv_interpretation": "\u27a1\ufe0f Mid-range - within Range"
    },
    {
      "ticker": "USDGBP",
      "name": "USD/GBP Currency Pair",
      "current_date": "2026-06-02 20:00",
      "current_price": 0.7426999807357788,
      "current_percentile": 55.77689243027888,
      "percentile_cohort": "medium_high",
      "zone_label": "50-70th percentile (Medium High)",
      "in_entry_zone": false,
      "regime": "mean_reversion",
      "is_mean_reverter": true,
      "is_momentum": false,
      "volatility_level": "Low",
      "live_expectancy": {
        "expected_win_rate": 0.6506024096385542,
        "expected_return_pct": 0.009808509317298214,
        "expected_holding_days": 0.6807228915662639,
        "expected_return_per_day_pct": 0.01440896059001333,
        "risk_adjusted_expectancy_pct": 0.009808509317298214,
        "sample_size": 249
      },
      "data_source": "4h",
      "prev_midday_percentile": 48.80952380952381,
      "change_since_prev_midday": 6.967368620755067,
      "prev_midday_price": 0.7434099912643433,
      "price_change_pct": -0.09550726206368487,
      "macdv_daily": 9.47,
      "macdv_daily_trend": "Neutral",
      "macdv_delta_1d": -1.78,
      "macdv_delta_5d": 0.39,
      "macdv_delta_10d": 0.7,
      "macdv_trend": "\u2192\u2197",
      "macdv_trend_label": "FLAT",
      "days_in_zone": 15,
      "next_threshold": null,
      "next_threshold_distance": null,
      "signal_crossover": null,
      "macdv_decay_accel": -1.29,
      "transition_type": "stable_ranging",
      "transition_score": 0,
      "macdv_zone": null,
      "macdv_zone_display": null,
      "macdv_categorical_percentile": null,
      "macdv_asymmetric_percentile": null,
      "macdv_interpretation": null
    },
    {
      "ticker": "GLD",
      "name": "SPDR Gold Trust",
      "current_date": "2026-06-02 12:00",
      "current_price": 411.9219970703125,
      "current_percentile": 57.76892430278885,
      "percentile_cohort": "medium_high",
      "zone_label": "50-70th percentile (Medium High)",
      "in_entry_zone": false,
      "regime": "momentum",
      "is_mean_reverter": false,
      "is_momentum": true,
      "volatility_level": "Low",
      "live_expectancy": {
        "expected_win_rate": 0.6527777777777778,
        "expected_return_pct": -0.010206481839588352,
        "expected_holding_days": 1.009259259259259,
        "expected_return_per_day_pct": -0.010112844391518735,
        "risk_adjusted_expectancy_pct": -0.010206481839588352,
        "sample_size": 72
      },
      "data_source": "4h",
      "prev_midday_percentile": 37.698412698412696,
      "change_since_prev_midday": 20.07051160437615,
      "prev_midday_price": 411.260009765625,
      "price_change_pct": 0.1609656394903952,
      "macdv_daily": -68.22,
      "macdv_daily_trend": "Bearish",
      "macdv_delta_1d": 0.02,
      "macdv_delta_5d": -0.45,
      "macdv_delta_10d": -2.73,
      "macdv_trend": "\u2192",
      "macdv_trend_label": "FLAT",
      "days_in_zone": 10,
      "next_threshold": null,
      "next_threshold_distance": null,
      "signal_crossover": null,
      "macdv_decay_accel": 0.69,
      "transition_type": "bearish_exhaustion",
      "transition_score": 44,
      "macdv_zone": "extreme_bullish",
      "macdv_zone_display": "Extreme Bullish (>+100)",
      "macdv_categorical_percentile": 8.13,
      "macdv_asymmetric_percentile": 90.0,
      "macdv_interpretation": "\u26a0\ufe0f Near bottom - weak within Extreme Bullish"
    },
    {
      "ticker": "SLV",
      "name": "iShares Silver Trust",
      "current_date": "2026-06-02 12:00",
      "current_price": 68.0,
      "current_percentile": 57.76892430278885,
      "percentile_cohort": "medium_high",
      "zone_label": "50-70th percentile (Medium High)",
      "in_entry_zone": false,
      "regime": "momentum",
      "is_mean_reverter": false,
      "is_momentum": true,
      "volatility_level": "Medium",
      "live_expectancy": {
        "expected_win_rate": 0.7291666666666666,
        "expected_return_pct": 0.7962504935808427,
        "expected_holding_days": 1.145833333333334,
        "expected_return_per_day_pct": 0.6949095216705532,
        "risk_adjusted_expectancy_pct": 0.5308336623872284,
        "sample_size": 48
      },
      "data_source": "4h",
      "prev_midday_percentile": 26.190476190476193,
      "change_since_prev_midday": 31.578448112312653,
      "prev_midday_price": 67.66999816894531,
      "price_change_pct": 0.48766342542348384,
      "macdv_daily": -22.09,
      "macdv_daily_trend": "Neutral",
      "macdv_delta_1d": -1.86,
      "macdv_delta_5d": -4.02,
      "macdv_delta_10d": -6.08,
      "macdv_trend": "\u2198",
      "macdv_trend_label": "DECEL",
      "days_in_zone": 11,
      "next_threshold": null,
      "next_threshold_distance": null,
      "signal_crossover": null,
      "macdv_decay_accel": 2.32,
      "transition_type": "pre_breakdown",
      "transition_score": 46,
      "macdv_zone": "strong_bullish",
      "macdv_zone_display": "Strong Bullish (+50 to +100)",
      "macdv_categorical_percentile": 38.1,
      "macdv_asymmetric_percentile": 75.0,
      "macdv_interpretation": "\ud83d\udcc9 Weakening - within Strong Bullish"
    },
    {
      "ticker": "NVDA",
      "name": "NVIDIA",
      "current_date": "2026-06-02 12:00",
      "current_price": 222.82000732421875,
      "current_percentile": 62.54980079681275,
      "percentile_cohort": "medium_high",
      "zone_label": "50-70th percentile (Medium High)",
      "in_entry_zone": false,
      "regime": "mean_reversion",
      "is_mean_reverter": true,
      "is_momentum": false,
      "volatility_level": "High",
      "live_expectancy": {
        "expected_win_rate": 0.6119797774601258,
        "expected_return_pct": 1.65,
        "expected_holding_days": 4.0,
        "expected_return_per_day_pct": 0.4125,
        "risk_adjusted_expectancy_pct": 0.825,
        "sample_size": 90
      },
      "data_source": "4h",
      "prev_midday_percentile": 72.61904761904762,
      "change_since_prev_midday": -10.069246822234874,
      "prev_midday_price": 224.36000061035156,
      "price_change_pct": -0.6863938678656609,
      "macdv_daily": 53.57,
      "macdv_daily_trend": "Bullish",
      "macdv_delta_1d": 1.78,
      "macdv_delta_5d": -5.25,
      "macdv_delta_10d": -7.19,
      "macdv_trend": "\u2198\u2198",
      "macdv_trend_label": "CRASH",
      "days_in_zone": 2,
      "next_threshold": 50,
      "next_threshold_distance": 3.6,
      "signal_crossover": null,
      "macdv_decay_accel": -1.41,
      "transition_type": "breakdown_risk",
      "transition_score": 42,
      "macdv_zone": "ranging",
      "macdv_zone_display": "Ranging (-50 to +50)",
      "macdv_categorical_percentile": 59.4,
      "macdv_asymmetric_percentile": 50.0,
      "macdv_interpretation": "\u27a1\ufe0f Mid-range - within Range"
    },
    {
      "ticker": "NQ1",
      "name": "E-mini Nasdaq 100 Futures",
      "current_date": "2026-06-02 16:00",
      "current_price": 30743.0,
      "current_percentile": 64.14342629482071,
      "percentile_cohort": "medium_high",
      "zone_label": "50-70th percentile (Medium High)",
      "in_entry_zone": false,
      "regime": "mean_reversion",
      "is_mean_reverter": true,
      "is_momentum": true,
      "volatility_level": "Medium-High",
      "live_expectancy": {
        "expected_win_rate": 0.6904761904761905,
        "expected_return_pct": 0.03294390602593901,
        "expected_holding_days": 0.5787037037037039,
        "expected_return_per_day_pct": 0.05692706961282259,
        "risk_adjusted_expectancy_pct": 0.021962604017292674,
        "sample_size": 252
      },
      "data_source": "4h",
      "prev_midday_percentile": 60.317460317460316,
      "change_since_prev_midday": 3.825965977360397,
      "prev_midday_price": 30566.25,
      "price_change_pct": 0.5782521571995256,
      "macdv_daily": 186.89,
      "macdv_daily_trend": "Bullish",
      "macdv_delta_1d": 3.48,
      "macdv_delta_5d": 1.37,
      "macdv_delta_10d": -1.85,
      "macdv_trend": "\u2192\u2197",
      "macdv_trend_label": "FLAT",
      "days_in_zone": 15,
      "next_threshold": null,
      "next_threshold_distance": null,
      "signal_crossover": "bullish",
      "macdv_decay_accel": 0.64,
      "transition_type": "peak_risk",
      "transition_score": 30,
      "macdv_zone": "ranging",
      "macdv_zone_display": "Ranging (-50 to +50)",
      "macdv_categorical_percentile": 22.43,
      "macdv_asymmetric_percentile": 50.0,
      "macdv_interpretation": "\u27a1\ufe0f Mid-range - within Range"
    },
    {
      "ticker": "OXY",
      "name": "Occidental Petroleum",
      "current_date": "2026-06-02 12:00",
      "current_price": 59.09000015258789,
      "current_percentile": 66.93227091633466,
      "percentile_cohort": "medium_high",
      "zone_label": "50-70th percentile (Medium High)",
      "in_entry_zone": false,
      "regime": "momentum",
      "is_mean_reverter": false,
      "is_momentum": true,
      "volatility_level": "Medium",
      "live_expectancy": {
        "expected_win_rate": 0.6721311475409836,
        "expected_return_pct": 0.12281666041787909,
        "expected_holding_days": 1.0136612021857923,
        "expected_return_per_day_pct": 0.12116144936103436,
        "risk_adjusted_expectancy_pct": 0.08187777361191939,
        "sample_size": 61
      },
      "data_source": "4h",
      "prev_midday_percentile": 69.04761904761905,
      "change_since_prev_midday": -2.1153481312843923,
      "prev_midday_price": 58.91999816894531,
      "price_change_pct": 0.2885301916594089,
      "macdv_daily": 5.33,
      "macdv_daily_trend": "Ranging",
      "macdv_delta_1d": 5.08,
      "macdv_delta_5d": -0.78,
      "macdv_delta_10d": 1.4,
      "macdv_trend": "\u2192",
      "macdv_trend_label": "FLAT",
      "days_in_zone": 15,
      "next_threshold": null,
      "next_threshold_distance": null,
      "signal_crossover": null,
      "macdv_decay_accel": -0.75,
      "transition_type": "stable_ranging",
      "transition_score": 0,
      "macdv_zone": "strong_bullish",
      "macdv_zone_display": "Strong Bullish (+50 to +100)",
      "macdv_categorical_percentile": 51.72,
      "macdv_asymmetric_percentile": 90.0,
      "macdv_interpretation": "\u27a1\ufe0f Mid-range - within Strong Bullish"
    },
    {
      "ticker": "XOM",
      "name": "ExxonMobil",
      "current_date": "2026-06-02 12:00",
      "current_price": 149.64999389648438,
      "current_percentile": 68.52589641434263,
      "percentile_cohort": "medium_high",
      "zone_label": "50-70th percentile (Medium High)",
      "in_entry_zone": false,
      "regime": "mean_reversion",
      "is_mean_reverter": true,
      "is_momentum": false,
      "volatility_level": "Medium",
      "live_expectancy": {
        "expected_win_rate": 0.75,
        "expected_return_pct": 0.37010933559113013,
        "expected_holding_days": 1.0735294117647052,
        "expected_return_per_day_pct": 0.34475938109858717,
        "risk_adjusted_expectancy_pct": 0.24673955706075343,
        "sample_size": 68
      },
      "data_source": "4h",
      "prev_midday_percentile": 40.87301587301587,
      "change_since_prev_midday": 27.652880541326752,
      "prev_midday_price": 149.3800048828125,
      "price_change_pct": 0.18073972743787187,
      "macdv_daily": -21.09,
      "macdv_daily_trend": "Ranging",
      "macdv_delta_1d": -0.96,
      "macdv_delta_5d": -8.01,
      "macdv_delta_10d": -3.25,
      "macdv_trend": "\u2198\u2198",
      "macdv_trend_label": "CRASH",
      "days_in_zone": 15,
      "next_threshold": null,
      "next_threshold_distance": null,
      "signal_crossover": null,
      "macdv_decay_accel": 0.41,
      "transition_type": "pre_breakdown",
      "transition_score": 51,
      "macdv_zone": "extreme_bullish",
      "macdv_zone_display": "Extreme Bullish (>+100)",
      "macdv_categorical_percentile": 66.67,
      "macdv_asymmetric_percentile": 99.0,
      "macdv_interpretation": "\ud83d\udcc8 Strengthening - within Extreme Bullish"
    },
    {
      "ticker": "JPM",
      "name": "JPMorgan Chase",
      "current_date": "2026-06-02 12:00",
      "current_price": 300.989990234375,
      "current_percentile": 72.50996015936255,
      "percentile_cohort": "high",
      "zone_label": "70-85th percentile (High)",
      "in_entry_zone": false,
      "regime": "mean_reversion",
      "is_mean_reverter": true,
      "is_momentum": false,
      "volatility_level": "Medium",
      "live_expectancy": {
        "expected_win_rate": 0.5217391304347826,
        "expected_return_pct": -0.34634044062578506,
        "expected_holding_days": 0.6195652173913042,
        "expected_return_per_day_pct": -0.5590056234661795,
        "risk_adjusted_expectancy_pct": -0.23089362708385672,
        "sample_size": 46
      },
      "data_source": "4h",
      "prev_midday_percentile": 33.33333333333333,
      "change_since_prev_midday": 39.17662682602922,
      "prev_midday_price": 296.5799865722656,
      "price_change_pct": 1.4869525462854587,
      "macdv_daily": -23.77,
      "macdv_daily_trend": "Neutral",
      "macdv_delta_1d": 2.68,
      "macdv_delta_5d": -3.48,
      "macdv_delta_10d": -1.03,
      "macdv_trend": "\u2198",
      "macdv_trend_label": "DECEL",
      "days_in_zone": 15,
      "next_threshold": null,
      "next_threshold_distance": null,
      "signal_crossover": null,
      "macdv_decay_accel": 8.09,
      "transition_type": "pre_breakdown",
      "transition_score": 45,
      "macdv_zone": "ranging",
      "macdv_zone_display": "Ranging (-50 to +50)",
      "macdv_categorical_percentile": 6.14,
      "macdv_asymmetric_percentile": 25.0,
      "macdv_interpretation": "\ud83d\udca1 Oversold - near bottom of Range"
    },
    {
      "ticker": "CVX",
      "name": "Chevron",
      "current_date": "2026-06-02 12:00",
      "current_price": 187.6300048828125,
      "current_percentile": 82.07171314741036,
      "percentile_cohort": "high",
      "zone_label": "70-85th percentile (High)",
      "in_entry_zone": false,
      "regime": "mean_reversion",
      "is_mean_reverter": true,
      "is_momentum": false,
      "volatility_level": "Medium",
      "live_expectancy": {
        "expected_win_rate": 0.47619047619047616,
        "expected_return_pct": 0.14853614643487573,
        "expected_holding_days": 0.8174603174603177,
        "expected_return_per_day_pct": 0.18170441214363434,
        "risk_adjusted_expectancy_pct": 0.09902409762325048,
        "sample_size": 42
      },
      "data_source": "4h",
      "prev_midday_percentile": 50.79365079365079,
      "change_since_prev_midday": 31.278062353759573,
      "prev_midday_price": 185.8300018310547,
      "price_change_pct": 0.9686288726371889,
      "macdv_daily": -16.9,
      "macdv_daily_trend": "Ranging",
      "macdv_delta_1d": 3.52,
      "macdv_delta_5d": -4.6,
      "macdv_delta_10d": -0.38,
      "macdv_trend": "\u2198",
      "macdv_trend_label": "DECEL",
      "days_in_zone": 15,
      "next_threshold": null,
      "next_threshold_distance": null,
      "signal_crossover": null,
      "macdv_decay_accel": 2.52,
      "transition_type": "stable_ranging",
      "transition_score": 0,
      "macdv_zone": "extreme_bullish",
      "macdv_zone_display": "Extreme Bullish (>+100)",
      "macdv_categorical_percentile": 95.24,
      "macdv_asymmetric_percentile": 99.0,
      "macdv_interpretation": "\ud83d\ude80 Very strong - near top of Extreme Bullish"
    },
    {
      "ticker": "TSM",
      "name": "Taiwan Semiconductor",
      "current_date": "2026-06-02 12:00",
      "current_price": 446.70001220703125,
      "current_percentile": 82.07171314741036,
      "percentile_cohort": "high",
      "zone_label": "70-85th percentile (High)",
      "in_entry_zone": false,
      "regime": "momentum",
      "is_mean_reverter": false,
      "is_momentum": true,
      "volatility_level": "High",
      "live_expectancy": {
        "expected_win_rate": 0.5681818181818182,
        "expected_return_pct": 0.341269180549031,
        "expected_holding_days": 0.7121212121212124,
        "expected_return_per_day_pct": 0.47922906204757526,
        "risk_adjusted_expectancy_pct": 0.1706345902745155,
        "sample_size": 44
      },
      "data_source": "4h",
      "prev_midday_percentile": 83.73015873015873,
      "change_since_prev_midday": -1.6584455827483708,
      "prev_midday_price": 435.6300048828125,
      "price_change_pct": 2.54114895671538,
      "macdv_daily": 83.69,
      "macdv_daily_trend": "Bullish",
      "macdv_delta_1d": 14.07,
      "macdv_delta_5d": 5.85,
      "macdv_delta_10d": 1.34,
      "macdv_trend": "\u2197\u2197",
      "macdv_trend_label": "ACC",
      "days_in_zone": 15,
      "next_threshold": null,
      "next_threshold_distance": null,
      "signal_crossover": null,
      "macdv_decay_accel": 8.82,
      "transition_type": "momentum_building",
      "transition_score": 46,
      "macdv_zone": "strong_bullish",
      "macdv_zone_display": "Strong Bullish (+50 to +100)",
      "macdv_categorical_percentile": 66.67,
      "macdv_asymmetric_percentile": 90.0,
      "macdv_interpretation": "\ud83d\udcc8 Strengthening - within Strong Bullish"
    },
    {
      "ticker": "BAC",
      "name": "Bank of America",
      "current_date": "2026-06-02 12:00",
      "current_price": 52.5,
      "current_percentile": 84.06374501992032,
      "percentile_cohort": "high",
      "zone_label": "70-85th percentile (High)",
      "in_entry_zone": false,
      "regime": "mean_reversion",
      "is_mean_reverter": true,
      "is_momentum": false,
      "volatility_level": "Medium",
      "live_expectancy": {
        "expected_win_rate": 0.6041666666666666,
        "expected_return_pct": 0.18597263439158399,
        "expected_holding_days": 0.84375,
        "expected_return_per_day_pct": 0.2204120111307662,
        "risk_adjusted_expectancy_pct": 0.123981756261056,
        "sample_size": 48
      },
      "data_source": "4h",
      "prev_midday_percentile": 60.71428571428571,
      "change_since_prev_midday": 23.34945930563461,
      "prev_midday_price": 51.5099983215332,
      "price_change_pct": 1.9219602227261914,
      "macdv_daily": 3.32,
      "macdv_daily_trend": "Neutral",
      "macdv_delta_1d": 8.71,
      "macdv_delta_5d": 1.73,
      "macdv_delta_10d": 2.83,
      "macdv_trend": "\u2192\u2197",
      "macdv_trend_label": "FLAT",
      "days_in_zone": 15,
      "next_threshold": null,
      "next_threshold_distance": null,
      "signal_crossover": null,
      "macdv_decay_accel": 6.76,
      "transition_type": "stable_ranging",
      "transition_score": 0,
      "macdv_zone": "ranging",
      "macdv_zone_display": "Ranging (-50 to +50)",
      "macdv_categorical_percentile": 16.13,
      "macdv_asymmetric_percentile": 50.0,
      "macdv_interpretation": "\ud83d\udca1 Oversold - near bottom of Range"
    },
    {
      "ticker": "AVGO",
      "name": "Broadcom Inc.",
      "current_date": "2026-06-02 12:00",
      "current_price": 481.5400085449219,
      "current_percentile": 96.41434262948208,
      "percentile_cohort": "extreme_high",
      "zone_label": "85-100th percentile (Extreme High)",
      "in_entry_zone": false,
      "regime": "momentum",
      "is_mean_reverter": false,
      "is_momentum": true,
      "volatility_level": "High",
      "live_expectancy": {
        "expected_win_rate": 0.5818418354760583,
        "expected_return_pct": 1.3173214285714285,
        "expected_holding_days": 4.0,
        "expected_return_per_day_pct": 0.32933035714285713,
        "risk_adjusted_expectancy_pct": 0.6586607142857143,
        "sample_size": 168
      },
      "data_source": "4h",
      "prev_midday_percentile": 90.47619047619048,
      "change_since_prev_midday": 5.938152153291597,
      "prev_midday_price": 459.9700012207031,
      "price_change_pct": 4.689437847462799,
      "macdv_daily": 89.89,
      "macdv_daily_trend": "Bullish",
      "macdv_delta_1d": 17.18,
      "macdv_delta_5d": 6.68,
      "macdv_delta_10d": -0.9,
      "macdv_trend": "\u2197\u2197",
      "macdv_trend_label": "ACC",
      "days_in_zone": 11,
      "next_threshold": null,
      "next_threshold_distance": null,
      "signal_crossover": null,
      "macdv_decay_accel": 6.0,
      "transition_type": "momentum_building",
      "transition_score": 53,
      "macdv_zone": "strong_bearish",
      "macdv_zone_display": "Strong Bearish (-100 to -50)",
      "macdv_categorical_percentile": 89.19,
      "macdv_asymmetric_percentile": 10.0,
      "macdv_interpretation": "\ud83d\udd04 Strong recovery - near top of Strong Bearish"
    }
  ],
  "summary": {
    "total_tickers": 32,
    "in_entry_zone": 5,
    "extreme_low_opportunities": 2,
    "low_opportunities": 3
  },
  "prev_midday_snapshot": {
    "market_date": "2026-06-01",
    "captured_at": "2026-06-01T16:00:00 (close, computed)",
    "timeframe": "4h",
    "from_fallback": true
  }
}
