{
  "timestamp": "2026-03-26T18:33:12.136784+00:00",
  "timeframe": "4h",
  "market_state": [
    {
      "ticker": "GOOGL",
      "name": "Google",
      "current_date": "2026-03-26 12:00",
      "current_price": 281.18499755859375,
      "current_percentile": 0.796812749003984,
      "percentile_cohort": "extreme_low",
      "zone_label": "\u22645th percentile (Extreme Low)",
      "in_entry_zone": true,
      "regime": "mean_reversion",
      "is_mean_reverter": true,
      "is_momentum": false,
      "volatility_level": "Medium",
      "live_expectancy": {
        "expected_win_rate": 0.7256179602887379,
        "expected_return_pct": 3.1,
        "expected_holding_days": 4.0,
        "expected_return_per_day_pct": 0.775,
        "risk_adjusted_expectancy_pct": 2.066666666666667,
        "sample_size": 18
      },
      "data_source": "4h",
      "prev_midday_percentile": 16.666666666666664,
      "change_since_prev_midday": -15.869853917662681,
      "prev_midday_price": 290.92999267578125,
      "price_change_pct": -3.349601403265264,
      "macdv_daily": -76.2,
      "macdv_daily_trend": "Bearish",
      "macdv_delta_1d": -13.79,
      "macdv_delta_5d": -8.31,
      "macdv_delta_10d": -3.04,
      "macdv_trend": "\u2198\u2198",
      "macdv_trend_label": "CRASH",
      "days_in_zone": 3,
      "next_threshold": null,
      "next_threshold_distance": null,
      "signal_crossover": null,
      "macdv_decay_accel": -3.84,
      "transition_type": "bearish_stable",
      "transition_score": 0,
      "macdv_zone": "strong_bullish",
      "macdv_zone_display": "Strong Bullish (+50 to +100)",
      "macdv_categorical_percentile": 77.63,
      "macdv_asymmetric_percentile": 75.0,
      "macdv_interpretation": "\ud83d\udcc8 Strengthening - within Strong Bullish"
    },
    {
      "ticker": "BTCUSD",
      "name": "Bitcoin USD",
      "current_date": "2026-03-26 16:00",
      "current_price": 68163.75,
      "current_percentile": 5.577689243027888,
      "percentile_cohort": "low",
      "zone_label": "5-15th percentile (Low)",
      "in_entry_zone": true,
      "regime": "momentum",
      "is_mean_reverter": false,
      "is_momentum": true,
      "volatility_level": "High",
      "live_expectancy": {
        "expected_win_rate": 0.5891891891891892,
        "expected_return_pct": -0.18119625627218988,
        "expected_holding_days": 0.9072072072072069,
        "expected_return_per_day_pct": -0.199729736307975,
        "risk_adjusted_expectancy_pct": -0.09059812813609494,
        "sample_size": 185
      },
      "data_source": "4h",
      "prev_midday_percentile": 63.095238095238095,
      "change_since_prev_midday": -57.517548852210204,
      "prev_midday_price": 71309.8828125,
      "price_change_pct": -4.411916957951459,
      "macdv_daily": -1.68,
      "macdv_daily_trend": "Ranging",
      "macdv_delta_1d": -6.63,
      "macdv_delta_5d": -1.92,
      "macdv_delta_10d": -2.04,
      "macdv_trend": "\u2192",
      "macdv_trend_label": "FLAT",
      "days_in_zone": 15,
      "next_threshold": null,
      "next_threshold_distance": null,
      "signal_crossover": "bearish",
      "macdv_decay_accel": -9.1,
      "transition_type": "stable_ranging",
      "transition_score": 0,
      "macdv_zone": "extreme_bearish",
      "macdv_zone_display": "Extreme Bearish (<-100)",
      "macdv_categorical_percentile": 31.25,
      "macdv_asymmetric_percentile": 10.0,
      "macdv_interpretation": "\u2198\ufe0f Weakening - within Extreme Bearish"
    },
    {
      "ticker": "NQ1",
      "name": "E-mini Nasdaq 100 Futures",
      "current_date": "2026-03-26 12:00",
      "current_price": 23873.25,
      "current_percentile": 8.764940239043826,
      "percentile_cohort": "low",
      "zone_label": "5-15th percentile (Low)",
      "in_entry_zone": true,
      "regime": "mean_reversion",
      "is_mean_reverter": true,
      "is_momentum": true,
      "volatility_level": "Medium-High",
      "live_expectancy": {
        "expected_win_rate": 0.6363636363636364,
        "expected_return_pct": -0.0018026571110191679,
        "expected_holding_days": 1.856060606060606,
        "expected_return_per_day_pct": -0.000971227504712368,
        "risk_adjusted_expectancy_pct": -0.0012017714073461118,
        "sample_size": 132
      },
      "data_source": "4h",
      "prev_midday_percentile": 57.53968253968254,
      "change_since_prev_midday": -48.774742300638714,
      "prev_midday_price": 24367.75,
      "price_change_pct": -2.0293215417919175,
      "macdv_daily": -50.24,
      "macdv_daily_trend": "Bearish",
      "macdv_delta_1d": -6.35,
      "macdv_delta_5d": -2.51,
      "macdv_delta_10d": -2.58,
      "macdv_trend": "\u2198",
      "macdv_trend_label": "DECEL",
      "days_in_zone": 1,
      "next_threshold": -50,
      "next_threshold_distance": -0.2,
      "signal_crossover": null,
      "macdv_decay_accel": -6.46,
      "transition_type": "bearish_exhaustion",
      "transition_score": 49,
      "macdv_zone": "ranging",
      "macdv_zone_display": "Ranging (-50 to +50)",
      "macdv_categorical_percentile": 22.43,
      "macdv_asymmetric_percentile": 50.0,
      "macdv_interpretation": "\u27a1\ufe0f Mid-range - within Range"
    },
    {
      "ticker": "ES1",
      "name": "E-mini S&P 500 Futures",
      "current_date": "2026-03-26 12:00",
      "current_price": 6540.5,
      "current_percentile": 11.952191235059761,
      "percentile_cohort": "low",
      "zone_label": "5-15th percentile (Low)",
      "in_entry_zone": true,
      "regime": "mean_reversion",
      "is_mean_reverter": true,
      "is_momentum": false,
      "volatility_level": "Medium",
      "live_expectancy": {
        "expected_win_rate": 0.6747967479674797,
        "expected_return_pct": 0.12208993909740948,
        "expected_holding_days": 1.8943089430894313,
        "expected_return_per_day_pct": 0.064450912055714,
        "risk_adjusted_expectancy_pct": 0.08139329273160632,
        "sample_size": 123
      },
      "data_source": "4h",
      "prev_midday_percentile": 72.22222222222221,
      "change_since_prev_midday": -60.27003098716246,
      "prev_midday_price": 6640.75,
      "price_change_pct": -1.5096186424726123,
      "macdv_daily": -68.55,
      "macdv_daily_trend": "Bearish",
      "macdv_delta_1d": -3.65,
      "macdv_delta_5d": -0.76,
      "macdv_delta_10d": -2.56,
      "macdv_trend": "\u2192",
      "macdv_trend_label": "FLAT",
      "days_in_zone": 10,
      "next_threshold": null,
      "next_threshold_distance": null,
      "signal_crossover": null,
      "macdv_decay_accel": -5.67,
      "transition_type": "bearish_exhaustion",
      "transition_score": 44,
      "macdv_zone": "ranging",
      "macdv_zone_display": "Ranging (-50 to +50)",
      "macdv_categorical_percentile": 42.86,
      "macdv_asymmetric_percentile": 50.0,
      "macdv_interpretation": "\u27a1\ufe0f Mid-range - within Range"
    },
    {
      "ticker": "MSFT",
      "name": "Microsoft",
      "current_date": "2026-03-26 12:00",
      "current_price": 366.3699951171875,
      "current_percentile": 13.94422310756972,
      "percentile_cohort": "low",
      "zone_label": "5-15th percentile (Low)",
      "in_entry_zone": true,
      "regime": "mean_reversion",
      "is_mean_reverter": true,
      "is_momentum": false,
      "volatility_level": "Medium",
      "live_expectancy": {
        "expected_win_rate": 0.7308496254906386,
        "expected_return_pct": 1.84,
        "expected_holding_days": 4.0,
        "expected_return_per_day_pct": 0.46,
        "risk_adjusted_expectancy_pct": 1.2266666666666668,
        "sample_size": 28
      },
      "data_source": "4h",
      "prev_midday_percentile": 10.714285714285714,
      "change_since_prev_midday": 3.229937393284006,
      "prev_midday_price": 371.0400085449219,
      "price_change_pct": -1.258627997031478,
      "macdv_daily": -129.25,
      "macdv_daily_trend": "Bearish",
      "macdv_delta_1d": -10.34,
      "macdv_delta_5d": -10.52,
      "macdv_delta_10d": -6.88,
      "macdv_trend": "\u2198\u2198",
      "macdv_trend_label": "CRASH",
      "days_in_zone": 3,
      "next_threshold": null,
      "next_threshold_distance": null,
      "signal_crossover": null,
      "macdv_decay_accel": 0.23,
      "transition_type": "bearish_stable",
      "transition_score": 0,
      "macdv_zone": "extreme_bearish",
      "macdv_zone_display": "Extreme Bearish (<-100)",
      "macdv_categorical_percentile": 16.67,
      "macdv_asymmetric_percentile": 10.0,
      "macdv_interpretation": "\u26a0\ufe0f Extreme weakness - near bottom of Extreme Bearish"
    },
    {
      "ticker": "TSM",
      "name": "Taiwan Semiconductor",
      "current_date": "2026-03-26 12:00",
      "current_price": 328.25,
      "current_percentile": 13.94422310756972,
      "percentile_cohort": "low",
      "zone_label": "5-15th percentile (Low)",
      "in_entry_zone": true,
      "regime": "momentum",
      "is_mean_reverter": false,
      "is_momentum": true,
      "volatility_level": "High",
      "live_expectancy": {
        "expected_win_rate": 0.5609756097560976,
        "expected_return_pct": 0.2123976707831515,
        "expected_holding_days": 1.861788617886179,
        "expected_return_per_day_pct": 0.11408259173068834,
        "risk_adjusted_expectancy_pct": 0.10619883539157575,
        "sample_size": 41
      },
      "data_source": "4h",
      "prev_midday_percentile": 69.04761904761905,
      "change_since_prev_midday": -55.10339594004933,
      "prev_midday_price": 347.75,
      "price_change_pct": -5.607476635514018,
      "macdv_daily": -33.38,
      "macdv_daily_trend": "Neutral",
      "macdv_delta_1d": -6.84,
      "macdv_delta_5d": -2.15,
      "macdv_delta_10d": -3.2,
      "macdv_trend": "\u2198",
      "macdv_trend_label": "DECEL",
      "days_in_zone": 15,
      "next_threshold": null,
      "next_threshold_distance": null,
      "signal_crossover": null,
      "macdv_decay_accel": -12.55,
      "transition_type": "pre_breakdown",
      "transition_score": 49,
      "macdv_zone": "strong_bullish",
      "macdv_zone_display": "Strong Bullish (+50 to +100)",
      "macdv_categorical_percentile": 66.67,
      "macdv_asymmetric_percentile": 90.0,
      "macdv_interpretation": "\ud83d\udcc8 Strengthening - within Strong Bullish"
    },
    {
      "ticker": "QQQ",
      "name": "Nasdaq 100 ETF",
      "current_date": "2026-03-26 12:00",
      "current_price": 575.8099975585938,
      "current_percentile": 15.139442231075698,
      "percentile_cohort": "medium_low",
      "zone_label": "15-30th percentile (Medium Low)",
      "in_entry_zone": false,
      "regime": "mean_reversion",
      "is_mean_reverter": true,
      "is_momentum": true,
      "volatility_level": "Medium",
      "live_expectancy": {
        "expected_win_rate": 0.7291666666666666,
        "expected_return_pct": -0.011475227486712744,
        "expected_holding_days": 2.8680555555555554,
        "expected_return_per_day_pct": -0.004001047840403475,
        "risk_adjusted_expectancy_pct": -0.007650151657808496,
        "sample_size": 48
      },
      "data_source": "4h",
      "prev_midday_percentile": 48.80952380952381,
      "change_since_prev_midday": -33.67008157844811,
      "prev_midday_price": 587.8200073242188,
      "price_change_pct": -2.0431440944473915,
      "macdv_daily": -68.25,
      "macdv_daily_trend": "Bearish",
      "macdv_delta_1d": -8.17,
      "macdv_delta_5d": -5.87,
      "macdv_delta_10d": -4.44,
      "macdv_trend": "\u2198\u2198",
      "macdv_trend_label": "CRASH",
      "days_in_zone": 4,
      "next_threshold": null,
      "next_threshold_distance": null,
      "signal_crossover": null,
      "macdv_decay_accel": -7.14,
      "transition_type": "bearish_stable",
      "transition_score": 0,
      "macdv_zone": "ranging",
      "macdv_zone_display": "Ranging (-50 to +50)",
      "macdv_categorical_percentile": 43.48,
      "macdv_asymmetric_percentile": 50.0,
      "macdv_interpretation": "\u27a1\ufe0f Mid-range - within Range"
    },
    {
      "ticker": "NVDA",
      "name": "NVIDIA",
      "current_date": "2026-03-26 12:00",
      "current_price": 172.25999450683594,
      "current_percentile": 17.52988047808765,
      "percentile_cohort": "medium_low",
      "zone_label": "15-30th percentile (Medium Low)",
      "in_entry_zone": false,
      "regime": "mean_reversion",
      "is_mean_reverter": true,
      "is_momentum": false,
      "volatility_level": "High",
      "live_expectancy": {
        "expected_win_rate": 0.522383175836637,
        "expected_return_pct": 0.43,
        "expected_holding_days": 4.0,
        "expected_return_per_day_pct": 0.1075,
        "risk_adjusted_expectancy_pct": 0.215,
        "sample_size": 27
      },
      "data_source": "4h",
      "prev_midday_percentile": 62.301587301587304,
      "change_since_prev_midday": -44.771706823499656,
      "prev_midday_price": 178.67999267578125,
      "price_change_pct": -3.5930145691210877,
      "macdv_daily": -48.29,
      "macdv_daily_trend": "Ranging",
      "macdv_delta_1d": -6.16,
      "macdv_delta_5d": -4.73,
      "macdv_delta_10d": -3.5,
      "macdv_trend": "\u2198",
      "macdv_trend_label": "DECEL",
      "days_in_zone": 15,
      "next_threshold": -50,
      "next_threshold_distance": 1.7,
      "signal_crossover": null,
      "macdv_decay_accel": -8.24,
      "transition_type": "pre_breakdown",
      "transition_score": 85,
      "macdv_zone": "ranging",
      "macdv_zone_display": "Ranging (-50 to +50)",
      "macdv_categorical_percentile": 59.4,
      "macdv_asymmetric_percentile": 50.0,
      "macdv_interpretation": "\u27a1\ufe0f Mid-range - within Range"
    },
    {
      "ticker": "UNH",
      "name": "UnitedHealth Group Inc.",
      "current_date": "2026-03-26 12:00",
      "current_price": 267.6300048828125,
      "current_percentile": 19.9203187250996,
      "percentile_cohort": "medium_low",
      "zone_label": "15-30th percentile (Medium Low)",
      "in_entry_zone": false,
      "regime": "momentum",
      "is_mean_reverter": false,
      "is_momentum": true,
      "volatility_level": "High",
      "live_expectancy": {
        "expected_win_rate": 0.6607142857142857,
        "expected_return_pct": 0.10435635023435297,
        "expected_holding_days": 2.4910714285714284,
        "expected_return_per_day_pct": 0.041892154932786856,
        "risk_adjusted_expectancy_pct": 0.052178175117176484,
        "sample_size": 56
      },
      "data_source": "4h",
      "prev_midday_percentile": 23.809523809523807,
      "change_since_prev_midday": -3.889205084424205,
      "prev_midday_price": 270.54998779296875,
      "price_change_pct": -1.079276674146698,
      "macdv_daily": -69.19,
      "macdv_daily_trend": "Bearish",
      "macdv_delta_1d": -4.9,
      "macdv_delta_5d": -6.1,
      "macdv_delta_10d": -1.9,
      "macdv_trend": "\u2198\u2198",
      "macdv_trend_label": "CRASH",
      "days_in_zone": 4,
      "next_threshold": null,
      "next_threshold_distance": null,
      "signal_crossover": null,
      "macdv_decay_accel": -1.11,
      "transition_type": "bearish_stable",
      "transition_score": 0,
      "macdv_zone": "extreme_bearish",
      "macdv_zone_display": "Extreme Bearish (<-100)",
      "macdv_categorical_percentile": 85.71,
      "macdv_asymmetric_percentile": 10.0,
      "macdv_interpretation": "\ud83d\udd04 Strong recovery - near top of Extreme Bearish"
    },
    {
      "ticker": "CNX1",
      "name": "CNX1 (LSE)",
      "current_date": "2026-03-26 16:00",
      "current_price": 102470.0,
      "current_percentile": 23.107569721115535,
      "percentile_cohort": "medium_low",
      "zone_label": "15-30th percentile (Medium Low)",
      "in_entry_zone": false,
      "regime": "mean_reversion",
      "is_mean_reverter": true,
      "is_momentum": false,
      "volatility_level": "Medium",
      "live_expectancy": {
        "expected_win_rate": 0.7183098591549296,
        "expected_return_pct": 0.05330740966222078,
        "expected_holding_days": 2.0117370892018775,
        "expected_return_per_day_pct": 0.026498198968618502,
        "risk_adjusted_expectancy_pct": 0.03553827310814719,
        "sample_size": 71
      },
      "data_source": "4h",
      "prev_midday_percentile": 36.904761904761905,
      "change_since_prev_midday": -13.79719218364637,
      "prev_midday_price": 103940.0,
      "price_change_pct": -1.414277467769867,
      "macdv_daily": -51.41,
      "macdv_daily_trend": "Bearish",
      "macdv_delta_1d": -8.82,
      "macdv_delta_5d": -7.62,
      "macdv_delta_10d": -5.22,
      "macdv_trend": "\u2198\u2198",
      "macdv_trend_label": "CRASH",
      "days_in_zone": 1,
      "next_threshold": -50,
      "next_threshold_distance": -1.4,
      "signal_crossover": null,
      "macdv_decay_accel": -6.69,
      "transition_type": "bearish_stable",
      "transition_score": 0,
      "macdv_zone": null,
      "macdv_zone_display": null,
      "macdv_categorical_percentile": null,
      "macdv_asymmetric_percentile": null,
      "macdv_interpretation": null
    },
    {
      "ticker": "TSLA",
      "name": "Tesla, Inc.",
      "current_date": "2026-03-26 12:00",
      "current_price": 375.2699890136719,
      "current_percentile": 24.701195219123505,
      "percentile_cohort": "medium_low",
      "zone_label": "15-30th percentile (Medium Low)",
      "in_entry_zone": false,
      "regime": "momentum",
      "is_mean_reverter": false,
      "is_momentum": true,
      "volatility_level": "High",
      "live_expectancy": {
        "expected_win_rate": 0.5045259903667294,
        "expected_return_pct": 0.07,
        "expected_holding_days": 4.0,
        "expected_return_per_day_pct": 0.0175,
        "risk_adjusted_expectancy_pct": 0.035,
        "sample_size": 124
      },
      "data_source": "4h",
      "prev_midday_percentile": 63.49206349206349,
      "change_since_prev_midday": -38.79086827293998,
      "prev_midday_price": 385.95001220703125,
      "price_change_pct": -2.7672037454504337,
      "macdv_daily": -70.55,
      "macdv_daily_trend": "Bearish",
      "macdv_delta_1d": -2.25,
      "macdv_delta_5d": -2.81,
      "macdv_delta_10d": -2.56,
      "macdv_trend": "\u2198",
      "macdv_trend_label": "DECEL",
      "days_in_zone": 6,
      "next_threshold": null,
      "next_threshold_distance": null,
      "signal_crossover": null,
      "macdv_decay_accel": -4.91,
      "transition_type": "bearish_exhaustion",
      "transition_score": 43,
      "macdv_zone": "ranging",
      "macdv_zone_display": "Ranging (-50 to +50)",
      "macdv_categorical_percentile": 4.76,
      "macdv_asymmetric_percentile": 50.0,
      "macdv_interpretation": "\ud83d\udca1 Oversold - near bottom of Range"
    },
    {
      "ticker": "AVGO",
      "name": "Broadcom Inc.",
      "current_date": "2026-03-26 12:00",
      "current_price": 310.3500061035156,
      "current_percentile": 25.099601593625497,
      "percentile_cohort": "medium_low",
      "zone_label": "15-30th percentile (Medium Low)",
      "in_entry_zone": false,
      "regime": "momentum",
      "is_mean_reverter": false,
      "is_momentum": true,
      "volatility_level": "High",
      "live_expectancy": {
        "expected_win_rate": 0.4806146075243581,
        "expected_return_pct": -0.21,
        "expected_holding_days": 4.0,
        "expected_return_per_day_pct": -0.0525,
        "risk_adjusted_expectancy_pct": -0.105,
        "sample_size": 119
      },
      "data_source": "4h",
      "prev_midday_percentile": 49.60317460317461,
      "change_since_prev_midday": -24.50357300954911,
      "prev_midday_price": 318.80999755859375,
      "price_change_pct": -2.653615482533063,
      "macdv_daily": -31.05,
      "macdv_daily_trend": "Ranging",
      "macdv_delta_1d": -5.23,
      "macdv_delta_5d": -2.7,
      "macdv_delta_10d": -3.96,
      "macdv_trend": "\u2198",
      "macdv_trend_label": "DECEL",
      "days_in_zone": 15,
      "next_threshold": null,
      "next_threshold_distance": null,
      "signal_crossover": null,
      "macdv_decay_accel": -4.21,
      "transition_type": "pre_breakdown",
      "transition_score": 50,
      "macdv_zone": "strong_bearish",
      "macdv_zone_display": "Strong Bearish (-100 to -50)",
      "macdv_categorical_percentile": 89.19,
      "macdv_asymmetric_percentile": 10.0,
      "macdv_interpretation": "\ud83d\udd04 Strong recovery - near top of Strong Bearish"
    },
    {
      "ticker": "CSP1",
      "name": "CSP1 (LSE)",
      "current_date": "2026-03-26 16:00",
      "current_price": 52493.95703125,
      "current_percentile": 27.091633466135455,
      "percentile_cohort": "medium_low",
      "zone_label": "15-30th percentile (Medium Low)",
      "in_entry_zone": false,
      "regime": "mean_reversion",
      "is_mean_reverter": true,
      "is_momentum": false,
      "volatility_level": "Medium",
      "live_expectancy": {
        "expected_win_rate": 0.746031746031746,
        "expected_return_pct": 0.005216065504547432,
        "expected_holding_days": 1.8359788359788356,
        "expected_return_per_day_pct": 0.00284102703273621,
        "risk_adjusted_expectancy_pct": 0.0034773770030316216,
        "sample_size": 63
      },
      "data_source": "4h",
      "prev_midday_percentile": 44.44444444444444,
      "change_since_prev_midday": -17.352810978308987,
      "prev_midday_price": 53014.0,
      "price_change_pct": -0.9809540286528087,
      "macdv_daily": -73.62,
      "macdv_daily_trend": "Bearish",
      "macdv_delta_1d": -7.09,
      "macdv_delta_5d": -6.74,
      "macdv_delta_10d": -6.26,
      "macdv_trend": "\u2198\u2198",
      "macdv_trend_label": "CRASH",
      "days_in_zone": 5,
      "next_threshold": null,
      "next_threshold_distance": null,
      "signal_crossover": null,
      "macdv_decay_accel": -6.61,
      "transition_type": "bearish_stable",
      "transition_score": 0,
      "macdv_zone": null,
      "macdv_zone_display": null,
      "macdv_categorical_percentile": null,
      "macdv_asymmetric_percentile": null,
      "macdv_interpretation": null
    },
    {
      "ticker": "GLD",
      "name": "SPDR Gold Trust",
      "current_date": "2026-03-26 12:00",
      "current_price": 402.1199951171875,
      "current_percentile": 27.091633466135455,
      "percentile_cohort": "medium_low",
      "zone_label": "15-30th percentile (Medium Low)",
      "in_entry_zone": false,
      "regime": "momentum",
      "is_mean_reverter": false,
      "is_momentum": true,
      "volatility_level": "Low",
      "live_expectancy": {
        "expected_win_rate": 0.8,
        "expected_return_pct": 0.7591517693672297,
        "expected_holding_days": 3.2333333333333334,
        "expected_return_per_day_pct": 0.2347892070207927,
        "risk_adjusted_expectancy_pct": 0.7591517693672297,
        "sample_size": 40
      },
      "data_source": "4h",
      "prev_midday_percentile": 11.507936507936508,
      "change_since_prev_midday": 15.583696958198948,
      "prev_midday_price": 416.2900085449219,
      "price_change_pct": -3.4038802606056997,
      "macdv_daily": -115.32,
      "macdv_daily_trend": "Bearish",
      "macdv_delta_1d": -12.39,
      "macdv_delta_5d": -18.8,
      "macdv_delta_10d": -16.35,
      "macdv_trend": "\u2198\u2198",
      "macdv_trend_label": "CRASH",
      "days_in_zone": 2,
      "next_threshold": null,
      "next_threshold_distance": null,
      "signal_crossover": null,
      "macdv_decay_accel": -5.33,
      "transition_type": "bearish_stable",
      "transition_score": 0,
      "macdv_zone": "extreme_bullish",
      "macdv_zone_display": "Extreme Bullish (>+100)",
      "macdv_categorical_percentile": 8.13,
      "macdv_asymmetric_percentile": 90.0,
      "macdv_interpretation": "\u26a0\ufe0f Near bottom - weak within Extreme Bullish"
    },
    {
      "ticker": "SPY",
      "name": "S&P 500 ETF",
      "current_date": "2026-03-26 12:00",
      "current_price": 647.1199951171875,
      "current_percentile": 30.677290836653388,
      "percentile_cohort": "medium",
      "zone_label": "30-50th percentile (Medium)",
      "in_entry_zone": false,
      "regime": "mean_reversion",
      "is_mean_reverter": true,
      "is_momentum": false,
      "volatility_level": "Low",
      "live_expectancy": {
        "expected_win_rate": 0.7818181818181819,
        "expected_return_pct": -0.05853831058607451,
        "expected_holding_days": 2.2969696969696973,
        "expected_return_per_day_pct": -0.025485016482064096,
        "risk_adjusted_expectancy_pct": -0.05853831058607451,
        "sample_size": 55
      },
      "data_source": "4h",
      "prev_midday_percentile": 53.17460317460318,
      "change_since_prev_midday": -22.49731233794979,
      "prev_midday_price": 656.8200073242188,
      "price_change_pct": -1.476814362971002,
      "macdv_daily": -87.73,
      "macdv_daily_trend": "Bearish",
      "macdv_delta_1d": -4.53,
      "macdv_delta_5d": -4.06,
      "macdv_delta_10d": -4.64,
      "macdv_trend": "\u2198",
      "macdv_trend_label": "DECEL",
      "days_in_zone": 10,
      "next_threshold": null,
      "next_threshold_distance": null,
      "signal_crossover": null,
      "macdv_decay_accel": -5.68,
      "transition_type": "bearish_exhaustion",
      "transition_score": 38,
      "macdv_zone": "ranging",
      "macdv_zone_display": "Ranging (-50 to +50)",
      "macdv_categorical_percentile": 61.54,
      "macdv_asymmetric_percentile": 50.0,
      "macdv_interpretation": "\u27a1\ufe0f Mid-range - within Range"
    },
    {
      "ticker": "SLV",
      "name": "iShares Silver Trust",
      "current_date": "2026-03-26 12:00",
      "current_price": 60.845001220703125,
      "current_percentile": 36.254980079681275,
      "percentile_cohort": "medium",
      "zone_label": "30-50th percentile (Medium)",
      "in_entry_zone": false,
      "regime": "momentum",
      "is_mean_reverter": false,
      "is_momentum": true,
      "volatility_level": "Medium",
      "live_expectancy": {
        "expected_win_rate": 0.5344827586206896,
        "expected_return_pct": -0.17523551742382512,
        "expected_holding_days": 1.4022988505747127,
        "expected_return_per_day_pct": -0.12496303291699004,
        "risk_adjusted_expectancy_pct": -0.11682367828255008,
        "sample_size": 58
      },
      "data_source": "4h",
      "prev_midday_percentile": 36.507936507936506,
      "change_since_prev_midday": -0.25295642825523146,
      "prev_midday_price": 65.20999908447266,
      "price_change_pct": -6.693755444031119,
      "macdv_daily": -96.59,
      "macdv_daily_trend": "Bearish",
      "macdv_delta_1d": -8.0,
      "macdv_delta_5d": -10.24,
      "macdv_delta_10d": -9.76,
      "macdv_trend": "\u2198\u2198",
      "macdv_trend_label": "CRASH",
      "days_in_zone": 5,
      "next_threshold": -100,
      "next_threshold_distance": 3.4,
      "signal_crossover": null,
      "macdv_decay_accel": -6.39,
      "transition_type": "bearish_stable",
      "transition_score": 0,
      "macdv_zone": "strong_bullish",
      "macdv_zone_display": "Strong Bullish (+50 to +100)",
      "macdv_categorical_percentile": 38.1,
      "macdv_asymmetric_percentile": 75.0,
      "macdv_interpretation": "\ud83d\udcc9 Weakening - within Strong Bullish"
    },
    {
      "ticker": "IGLS",
      "name": "IGLS (London)",
      "current_date": "2026-03-26 16:00",
      "current_price": 125.50740051269531,
      "current_percentile": 37.45019920318725,
      "percentile_cohort": "medium",
      "zone_label": "30-50th percentile (Medium)",
      "in_entry_zone": false,
      "regime": "mean_reversion",
      "is_mean_reverter": true,
      "is_momentum": false,
      "volatility_level": "Medium",
      "live_expectancy": {
        "expected_win_rate": 0.8977272727272727,
        "expected_return_pct": 0.044394113787068916,
        "expected_holding_days": 1.9924242424242415,
        "expected_return_per_day_pct": 0.02228145634940342,
        "risk_adjusted_expectancy_pct": 0.029596075858045943,
        "sample_size": 88
      },
      "data_source": "4h",
      "prev_midday_percentile": 14.682539682539684,
      "change_since_prev_midday": 22.76765952064757,
      "prev_midday_price": 125.80000305175781,
      "price_change_pct": -0.23259342763458815,
      "macdv_daily": -55.08,
      "macdv_daily_trend": "Bearish",
      "macdv_delta_1d": -2.35,
      "macdv_delta_5d": -2.52,
      "macdv_delta_10d": -3.67,
      "macdv_trend": "\u2198",
      "macdv_trend_label": "DECEL",
      "days_in_zone": 5,
      "next_threshold": -50,
      "next_threshold_distance": -5.1,
      "signal_crossover": null,
      "macdv_decay_accel": -4.22,
      "transition_type": "bearish_exhaustion",
      "transition_score": 48,
      "macdv_zone": null,
      "macdv_zone_display": null,
      "macdv_categorical_percentile": null,
      "macdv_asymmetric_percentile": null,
      "macdv_interpretation": null
    },
    {
      "ticker": "AMZN",
      "name": "Amazon.com Inc.",
      "current_date": "2026-03-26 12:00",
      "current_price": 208.25079345703125,
      "current_percentile": 43.02788844621514,
      "percentile_cohort": "medium",
      "zone_label": "30-50th percentile (Medium)",
      "in_entry_zone": false,
      "regime": "mean_reversion",
      "is_mean_reverter": true,
      "is_momentum": false,
      "volatility_level": "Medium",
      "live_expectancy": {
        "expected_win_rate": 0.45161290322580644,
        "expected_return_pct": -0.8970291320067334,
        "expected_holding_days": 1.8145161290322578,
        "expected_return_per_day_pct": -0.4943627216392665,
        "risk_adjusted_expectancy_pct": -0.5980194213378223,
        "sample_size": 62
      },
      "data_source": "4h",
      "prev_midday_percentile": 74.60317460317461,
      "change_since_prev_midday": -31.57528615695947,
      "prev_midday_price": 211.7100067138672,
      "price_change_pct": -1.6339394204975746,
      "macdv_daily": -35.83,
      "macdv_daily_trend": "Neutral",
      "macdv_delta_1d": -0.29,
      "macdv_delta_5d": 0.14,
      "macdv_delta_10d": -0.07,
      "macdv_trend": "\u2192\u2197",
      "macdv_trend_label": "FLAT",
      "days_in_zone": 15,
      "next_threshold": null,
      "next_threshold_distance": null,
      "signal_crossover": null,
      "macdv_decay_accel": -6.09,
      "transition_type": "stable_ranging",
      "transition_score": 0,
      "macdv_zone": "ranging",
      "macdv_zone_display": "Ranging (-50 to +50)",
      "macdv_categorical_percentile": 79.2,
      "macdv_asymmetric_percentile": 75.0,
      "macdv_interpretation": "\u27a1\ufe0f Mid-range - within Range"
    },
    {
      "ticker": "JPM",
      "name": "JPMorgan Chase",
      "current_date": "2026-03-26 12:00",
      "current_price": 291.52099609375,
      "current_percentile": 50.59760956175299,
      "percentile_cohort": "medium_high",
      "zone_label": "50-70th percentile (Medium High)",
      "in_entry_zone": false,
      "regime": "mean_reversion",
      "is_mean_reverter": true,
      "is_momentum": false,
      "volatility_level": "Medium",
      "live_expectancy": {
        "expected_win_rate": 0.631578947368421,
        "expected_return_pct": -0.1484397115338434,
        "expected_holding_days": 1.0350877192982453,
        "expected_return_per_day_pct": -0.14340785690557756,
        "risk_adjusted_expectancy_pct": -0.09895980768922892,
        "sample_size": 57
      },
      "data_source": "4h",
      "prev_midday_percentile": 98.80952380952381,
      "change_since_prev_midday": -48.21191424777082,
      "prev_midday_price": 295.4200134277344,
      "price_change_pct": -1.319821662975502,
      "macdv_daily": -45.61,
      "macdv_daily_trend": "Neutral",
      "macdv_delta_1d": 4.74,
      "macdv_delta_5d": 5.55,
      "macdv_delta_10d": 2.55,
      "macdv_trend": "\u2197\u2197",
      "macdv_trend_label": "ACC",
      "days_in_zone": 1,
      "next_threshold": -50,
      "next_threshold_distance": 4.4,
      "signal_crossover": null,
      "macdv_decay_accel": -5.76,
      "transition_type": "stable_ranging",
      "transition_score": 0,
      "macdv_zone": "ranging",
      "macdv_zone_display": "Ranging (-50 to +50)",
      "macdv_categorical_percentile": 6.14,
      "macdv_asymmetric_percentile": 25.0,
      "macdv_interpretation": "\ud83d\udca1 Oversold - near bottom of Range"
    },
    {
      "ticker": "BRK-B",
      "name": "Berkshire Hathaway Inc. Class B",
      "current_date": "2026-03-26 12:00",
      "current_price": 476.1099853515625,
      "current_percentile": 54.581673306772906,
      "percentile_cohort": "medium_high",
      "zone_label": "50-70th percentile (Medium High)",
      "in_entry_zone": false,
      "regime": "momentum",
      "is_mean_reverter": false,
      "is_momentum": true,
      "volatility_level": "Low",
      "live_expectancy": {
        "expected_win_rate": 0.5535714285714286,
        "expected_return_pct": -0.01689235843153084,
        "expected_holding_days": 1.3333333333333335,
        "expected_return_per_day_pct": -0.012669268823648128,
        "risk_adjusted_expectancy_pct": -0.01689235843153084,
        "sample_size": 56
      },
      "data_source": "4h",
      "prev_midday_percentile": 15.476190476190476,
      "change_since_prev_midday": 39.10548283058243,
      "prev_midday_price": 476.19000244140625,
      "price_change_pct": -0.016803605584641786,
      "macdv_daily": -57.72,
      "macdv_daily_trend": "Bearish",
      "macdv_delta_1d": -5.66,
      "macdv_delta_5d": -6.3,
      "macdv_delta_10d": -5.32,
      "macdv_trend": "\u2198\u2198",
      "macdv_trend_label": "CRASH",
      "days_in_zone": 2,
      "next_threshold": -50,
      "next_threshold_distance": -7.7,
      "signal_crossover": null,
      "macdv_decay_accel": 1.19,
      "transition_type": "bearish_stable",
      "transition_score": 0,
      "macdv_zone": "strong_bearish",
      "macdv_zone_display": "Strong Bearish (-100 to -50)",
      "macdv_categorical_percentile": 80.85,
      "macdv_asymmetric_percentile": 25.0,
      "macdv_interpretation": "\ud83d\udd04 Strong recovery - near top of Strong Bearish"
    },
    {
      "ticker": "XOM",
      "name": "ExxonMobil",
      "current_date": "2026-03-26 12:00",
      "current_price": 165.3300018310547,
      "current_percentile": 56.573705179282875,
      "percentile_cohort": "medium_high",
      "zone_label": "50-70th percentile (Medium High)",
      "in_entry_zone": false,
      "regime": "mean_reversion",
      "is_mean_reverter": true,
      "is_momentum": false,
      "volatility_level": "Medium",
      "live_expectancy": {
        "expected_win_rate": 0.703125,
        "expected_return_pct": 0.22141128380611633,
        "expected_holding_days": 1.223958333333334,
        "expected_return_per_day_pct": 0.1808977297479758,
        "risk_adjusted_expectancy_pct": 0.14760752253741088,
        "sample_size": 64
      },
      "data_source": "4h",
      "prev_midday_percentile": 64.28571428571429,
      "change_since_prev_midday": -7.712009106431417,
      "prev_midday_price": 163.25999450683594,
      "price_change_pct": 1.2679207361679017,
      "macdv_daily": 117.22,
      "macdv_daily_trend": "Bullish",
      "macdv_delta_1d": 6.62,
      "macdv_delta_5d": 5.19,
      "macdv_delta_10d": 4.51,
      "macdv_trend": "\u2197\u2197",
      "macdv_trend_label": "ACC",
      "days_in_zone": 3,
      "next_threshold": null,
      "next_threshold_distance": null,
      "signal_crossover": null,
      "macdv_decay_accel": 2.3,
      "transition_type": "momentum_building",
      "transition_score": 41,
      "macdv_zone": "extreme_bullish",
      "macdv_zone_display": "Extreme Bullish (>+100)",
      "macdv_categorical_percentile": 66.67,
      "macdv_asymmetric_percentile": 99.0,
      "macdv_interpretation": "\ud83d\udcc8 Strengthening - within Extreme Bullish"
    },
    {
      "ticker": "CVX",
      "name": "Chevron",
      "current_date": "2026-03-26 12:00",
      "current_price": 208.86500549316406,
      "current_percentile": 56.573705179282875,
      "percentile_cohort": "medium_high",
      "zone_label": "50-70th percentile (Medium High)",
      "in_entry_zone": false,
      "regime": "mean_reversion",
      "is_mean_reverter": true,
      "is_momentum": false,
      "volatility_level": "Medium",
      "live_expectancy": {
        "expected_win_rate": 0.7,
        "expected_return_pct": 0.18983919906559021,
        "expected_holding_days": 1.3111111111111113,
        "expected_return_per_day_pct": 0.14479260945680608,
        "risk_adjusted_expectancy_pct": 0.1265594660437268,
        "sample_size": 60
      },
      "data_source": "4h",
      "prev_midday_percentile": 46.03174603174603,
      "change_since_prev_midday": 10.541959147536843,
      "prev_midday_price": 205.14999389648438,
      "price_change_pct": 1.8108758017093711,
      "macdv_daily": 171.17,
      "macdv_daily_trend": "Bullish",
      "macdv_delta_1d": 5.25,
      "macdv_delta_5d": 4.26,
      "macdv_delta_10d": 4.49,
      "macdv_trend": "\u2197",
      "macdv_trend_label": "STR",
      "days_in_zone": 15,
      "next_threshold": null,
      "next_threshold_distance": null,
      "signal_crossover": null,
      "macdv_decay_accel": 0.5,
      "transition_type": "momentum_building",
      "transition_score": 34,
      "macdv_zone": "extreme_bullish",
      "macdv_zone_display": "Extreme Bullish (>+100)",
      "macdv_categorical_percentile": 95.24,
      "macdv_asymmetric_percentile": 99.0,
      "macdv_interpretation": "\ud83d\ude80 Very strong - near top of Extreme Bullish"
    },
    {
      "ticker": "WMT",
      "name": "Walmart Inc.",
      "current_date": "2026-03-26 12:00",
      "current_price": 122.55000305175781,
      "current_percentile": 64.5418326693227,
      "percentile_cohort": "medium_high",
      "zone_label": "50-70th percentile (Medium High)",
      "in_entry_zone": false,
      "regime": "momentum",
      "is_mean_reverter": false,
      "is_momentum": true,
      "volatility_level": "Medium",
      "live_expectancy": {
        "expected_win_rate": 0.5671641791044776,
        "expected_return_pct": -0.11738541317487071,
        "expected_holding_days": 1.0671641791044773,
        "expected_return_per_day_pct": -0.10999752003799078,
        "risk_adjusted_expectancy_pct": -0.07825694211658048,
        "sample_size": 67
      },
      "data_source": "4h",
      "prev_midday_percentile": 56.74603174603175,
      "change_since_prev_midday": 7.795800923290955,
      "prev_midday_price": 123.05999755859375,
      "price_change_pct": -0.41442752881017153,
      "macdv_daily": -23.21,
      "macdv_daily_trend": "Ranging",
      "macdv_delta_1d": 0.75,
      "macdv_delta_5d": -3.17,
      "macdv_delta_10d": -3.4,
      "macdv_trend": "\u2198",
      "macdv_trend_label": "DECEL",
      "days_in_zone": 15,
      "next_threshold": null,
      "next_threshold_distance": null,
      "signal_crossover": null,
      "macdv_decay_accel": -0.41,
      "transition_type": "pre_breakdown",
      "transition_score": 43,
      "macdv_zone": "strong_bullish",
      "macdv_zone_display": "Strong Bullish (+50 to +100)",
      "macdv_categorical_percentile": 95.06,
      "macdv_asymmetric_percentile": 90.0,
      "macdv_interpretation": "\ud83d\ude80 Very strong - near top of Strong Bullish"
    },
    {
      "ticker": "US10",
      "name": "US 10-Year Treasury Yield",
      "current_date": "2026-03-26 12:00",
      "current_price": 4.418000221252441,
      "current_percentile": 64.5418326693227,
      "percentile_cohort": "medium_high",
      "zone_label": "50-70th percentile (Medium High)",
      "in_entry_zone": false,
      "regime": "mean_reversion",
      "is_mean_reverter": true,
      "is_momentum": false,
      "volatility_level": "Low",
      "live_expectancy": {
        "expected_win_rate": 0.5555555555555556,
        "expected_return_pct": -0.04793313488910716,
        "expected_holding_days": 1.2757201646090537,
        "expected_return_per_day_pct": -0.03757339283242915,
        "risk_adjusted_expectancy_pct": -0.04793313488910716,
        "sample_size": 81
      },
      "data_source": "4h",
      "prev_midday_percentile": 67.06349206349206,
      "change_since_prev_midday": -2.5216593941693617,
      "prev_midday_price": 4.328000068664551,
      "price_change_pct": 2.0794859325328314,
      "macdv_daily": 102.55,
      "macdv_daily_trend": "Bullish",
      "macdv_delta_1d": 7.2,
      "macdv_delta_5d": 8.75,
      "macdv_delta_10d": 8.7,
      "macdv_trend": "\u2197\u2197",
      "macdv_trend_label": "ACC",
      "days_in_zone": 1,
      "next_threshold": 100,
      "next_threshold_distance": 2.5,
      "signal_crossover": null,
      "macdv_decay_accel": 9.32,
      "transition_type": "momentum_building",
      "transition_score": 70,
      "macdv_zone": "strong_bullish",
      "macdv_zone_display": "Strong Bullish (+50 to +100)",
      "macdv_categorical_percentile": 71.43,
      "macdv_asymmetric_percentile": 75.0,
      "macdv_interpretation": "\ud83d\udcc8 Strengthening - within Strong Bullish"
    },
    {
      "ticker": "LLY",
      "name": "Eli Lilly and Company",
      "current_date": "2026-03-26 12:00",
      "current_price": 901.9500122070312,
      "current_percentile": 69.32270916334662,
      "percentile_cohort": "medium_high",
      "zone_label": "50-70th percentile (Medium High)",
      "in_entry_zone": false,
      "regime": "momentum",
      "is_mean_reverter": false,
      "is_momentum": true,
      "volatility_level": "High",
      "live_expectancy": {
        "expected_win_rate": 0.6885245901639344,
        "expected_return_pct": 0.09112066106792957,
        "expected_holding_days": 1.2404371584699456,
        "expected_return_per_day_pct": 0.07345850649969651,
        "risk_adjusted_expectancy_pct": 0.045560330533964785,
        "sample_size": 61
      },
      "data_source": "4h",
      "prev_midday_percentile": 56.34920634920635,
      "change_since_prev_midday": 12.973502814140268,
      "prev_midday_price": 916.3099975585938,
      "price_change_pct": -1.567153625936974,
      "macdv_daily": -122.07,
      "macdv_daily_trend": "Bearish",
      "macdv_delta_1d": -3.86,
      "macdv_delta_5d": -6.42,
      "macdv_delta_10d": -8.37,
      "macdv_trend": "\u2198\u2198",
      "macdv_trend_label": "CRASH",
      "days_in_zone": 4,
      "next_threshold": null,
      "next_threshold_distance": null,
      "signal_crossover": null,
      "macdv_decay_accel": -2.43,
      "transition_type": "bearish_stable",
      "transition_score": 0,
      "macdv_zone": "ranging",
      "macdv_zone_display": "Ranging (-50 to +50)",
      "macdv_categorical_percentile": 20.35,
      "macdv_asymmetric_percentile": 25.0,
      "macdv_interpretation": "\u27a1\ufe0f Mid-range - within Range"
    },
    {
      "ticker": "BAC",
      "name": "Bank of America",
      "current_date": "2026-03-26 12:00",
      "current_price": 48.28499984741211,
      "current_percentile": 70.5179282868526,
      "percentile_cohort": "high",
      "zone_label": "70-85th percentile (High)",
      "in_entry_zone": false,
      "regime": "mean_reversion",
      "is_mean_reverter": true,
      "is_momentum": false,
      "volatility_level": "Medium",
      "live_expectancy": {
        "expected_win_rate": 0.5833333333333334,
        "expected_return_pct": -0.0016210605668138627,
        "expected_holding_days": 0.7453703703703707,
        "expected_return_per_day_pct": -0.002174839021315492,
        "risk_adjusted_expectancy_pct": -0.0010807070445425751,
        "sample_size": 36
      },
      "data_source": "4h",
      "prev_midday_percentile": 98.4126984126984,
      "change_since_prev_midday": -27.89477012584581,
      "prev_midday_price": 48.75,
      "price_change_pct": -0.9538464668469551,
      "macdv_daily": -69.43,
      "macdv_daily_trend": "Bearish",
      "macdv_delta_1d": 7.37,
      "macdv_delta_5d": 5.9,
      "macdv_delta_10d": 1.76,
      "macdv_trend": "\u2197\u2197",
      "macdv_trend_label": "ACC",
      "days_in_zone": 4,
      "next_threshold": null,
      "next_threshold_distance": null,
      "signal_crossover": null,
      "macdv_decay_accel": -4.22,
      "transition_type": "bearish_recovery",
      "transition_score": 68,
      "macdv_zone": "ranging",
      "macdv_zone_display": "Ranging (-50 to +50)",
      "macdv_categorical_percentile": 16.13,
      "macdv_asymmetric_percentile": 50.0,
      "macdv_interpretation": "\ud83d\udca1 Oversold - near bottom of Range"
    },
    {
      "ticker": "USDGBP",
      "name": "USD/GBP Currency Pair",
      "current_date": "2026-03-26 16:00",
      "current_price": 0.7505940198898315,
      "current_percentile": 72.50996015936255,
      "percentile_cohort": "high",
      "zone_label": "70-85th percentile (High)",
      "in_entry_zone": false,
      "regime": "mean_reversion",
      "is_mean_reverter": true,
      "is_momentum": false,
      "volatility_level": "Low",
      "live_expectancy": {
        "expected_win_rate": 0.527363184079602,
        "expected_return_pct": -0.010041771610724289,
        "expected_holding_days": 0.4419568822553903,
        "expected_return_per_day_pct": -0.02272115677773635,
        "risk_adjusted_expectancy_pct": -0.010041771610724289,
        "sample_size": 201
      },
      "data_source": "4h",
      "prev_midday_percentile": 25.396825396825395,
      "change_since_prev_midday": 47.11313476253716,
      "prev_midday_price": 0.7453600168228149,
      "price_change_pct": 0.7022114077606627,
      "macdv_daily": 33.37,
      "macdv_daily_trend": "Neutral",
      "macdv_delta_1d": 1.36,
      "macdv_delta_5d": -5.82,
      "macdv_delta_10d": -1.69,
      "macdv_trend": "\u2198\u2198",
      "macdv_trend_label": "CRASH",
      "days_in_zone": 4,
      "next_threshold": null,
      "next_threshold_distance": null,
      "signal_crossover": null,
      "macdv_decay_accel": 6.6,
      "transition_type": "stable_ranging",
      "transition_score": 0,
      "macdv_zone": null,
      "macdv_zone_display": null,
      "macdv_categorical_percentile": null,
      "macdv_asymmetric_percentile": null,
      "macdv_interpretation": null
    },
    {
      "ticker": "OXY",
      "name": "Occidental Petroleum",
      "current_date": "2026-03-26 12:00",
      "current_price": 63.56999969482422,
      "current_percentile": 76.49402390438247,
      "percentile_cohort": "high",
      "zone_label": "70-85th percentile (High)",
      "in_entry_zone": false,
      "regime": "momentum",
      "is_mean_reverter": false,
      "is_momentum": true,
      "volatility_level": "Medium",
      "live_expectancy": {
        "expected_win_rate": 0.3902439024390244,
        "expected_return_pct": 0.12629117415344907,
        "expected_holding_days": 0.5121951219512197,
        "expected_return_per_day_pct": 0.24656848287101948,
        "risk_adjusted_expectancy_pct": 0.08419411610229938,
        "sample_size": 41
      },
      "data_source": "4h",
      "prev_midday_percentile": 54.761904761904766,
      "change_since_prev_midday": 21.732119142477707,
      "prev_midday_price": 61.849998474121094,
      "price_change_pct": 2.780923626736705,
      "macdv_daily": 165.37,
      "macdv_daily_trend": "Bullish",
      "macdv_delta_1d": 5.84,
      "macdv_delta_5d": 3.14,
      "macdv_delta_10d": 2.96,
      "macdv_trend": "\u2197",
      "macdv_trend_label": "STR",
      "days_in_zone": 15,
      "next_threshold": null,
      "next_threshold_distance": null,
      "signal_crossover": null,
      "macdv_decay_accel": 3.73,
      "transition_type": "momentum_building",
      "transition_score": 25,
      "macdv_zone": "strong_bullish",
      "macdv_zone_display": "Strong Bullish (+50 to +100)",
      "macdv_categorical_percentile": 51.72,
      "macdv_asymmetric_percentile": 90.0,
      "macdv_interpretation": "\u27a1\ufe0f Mid-range - within Strong Bullish"
    },
    {
      "ticker": "VIX",
      "name": "CBOE Volatility Index",
      "current_date": "2026-03-26 12:00",
      "current_price": 28.209999084472656,
      "current_percentile": 77.68924302788844,
      "percentile_cohort": "high",
      "zone_label": "70-85th percentile (High)",
      "in_entry_zone": false,
      "regime": "mean_reversion",
      "is_mean_reverter": true,
      "is_momentum": false,
      "volatility_level": "High",
      "live_expectancy": {
        "expected_win_rate": 0.49612403100775193,
        "expected_return_pct": 0.43089993721315967,
        "expected_holding_days": 0.2726098191214474,
        "expected_return_per_day_pct": 1.580647163047323,
        "risk_adjusted_expectancy_pct": 0.21544996860657983,
        "sample_size": 129
      },
      "data_source": "4h",
      "prev_midday_percentile": 25.0,
      "change_since_prev_midday": 52.68924302788844,
      "prev_midday_price": 25.329999923706055,
      "price_change_pct": 11.369913815401333,
      "macdv_daily": 46.05,
      "macdv_daily_trend": "Neutral",
      "macdv_delta_1d": 3.25,
      "macdv_delta_5d": 0.23,
      "macdv_delta_10d": -0.96,
      "macdv_trend": "\u2192\u2197",
      "macdv_trend_label": "FLAT",
      "days_in_zone": 8,
      "next_threshold": 50,
      "next_threshold_distance": -4.0,
      "signal_crossover": "bullish",
      "macdv_decay_accel": 5.25,
      "transition_type": "stable_ranging",
      "transition_score": 0,
      "macdv_zone": "ranging",
      "macdv_zone_display": "Ranging (-50 to +50)",
      "macdv_categorical_percentile": 86.36,
      "macdv_asymmetric_percentile": 90.0,
      "macdv_interpretation": "\ud83d\udcc8 Strengthening - near top of Range"
    },
    {
      "ticker": "NFLX",
      "name": "Netflix Inc.",
      "current_date": "2026-03-26 12:00",
      "current_price": 93.9749984741211,
      "current_percentile": 82.86852589641434,
      "percentile_cohort": "high",
      "zone_label": "70-85th percentile (High)",
      "in_entry_zone": false,
      "regime": "momentum",
      "is_mean_reverter": false,
      "is_momentum": true,
      "volatility_level": "High",
      "live_expectancy": {
        "expected_win_rate": 0.5768331494855323,
        "expected_return_pct": 0.75,
        "expected_holding_days": 4.0,
        "expected_return_per_day_pct": 0.1875,
        "risk_adjusted_expectancy_pct": 0.375,
        "sample_size": 115
      },
      "data_source": "4h",
      "prev_midday_percentile": 20.238095238095237,
      "change_since_prev_midday": 62.6304306583191,
      "prev_midday_price": 92.27999877929688,
      "price_change_pct": 1.8368007339034491,
      "macdv_daily": 46.89,
      "macdv_daily_trend": "Neutral",
      "macdv_delta_1d": -3.17,
      "macdv_delta_5d": -7.08,
      "macdv_delta_10d": -7.15,
      "macdv_trend": "\u2198\u2198",
      "macdv_trend_label": "CRASH",
      "days_in_zone": 1,
      "next_threshold": 50,
      "next_threshold_distance": -3.1,
      "signal_crossover": null,
      "macdv_decay_accel": 2.56,
      "transition_type": "stable_ranging",
      "transition_score": 0,
      "macdv_zone": "extreme_bearish",
      "macdv_zone_display": "Extreme Bearish (<-100)",
      "macdv_categorical_percentile": 2.63,
      "macdv_asymmetric_percentile": 10.0,
      "macdv_interpretation": "\u26a0\ufe0f Extreme weakness - near bottom of Extreme Bearish"
    },
    {
      "ticker": "COST",
      "name": "Costco",
      "current_date": "2026-03-26 12:00",
      "current_price": 983.52001953125,
      "current_percentile": 84.86055776892431,
      "percentile_cohort": "high",
      "zone_label": "70-85th percentile (High)",
      "in_entry_zone": false,
      "regime": "mean_reversion",
      "is_mean_reverter": true,
      "is_momentum": false,
      "volatility_level": "Medium",
      "live_expectancy": {
        "expected_win_rate": 0.4727272727272727,
        "expected_return_pct": 0.10481750286867375,
        "expected_holding_days": 0.6121212121212122,
        "expected_return_per_day_pct": 0.1712365145874373,
        "risk_adjusted_expectancy_pct": 0.0698783352457825,
        "sample_size": 55
      },
      "data_source": "4h",
      "prev_midday_percentile": 33.730158730158735,
      "change_since_prev_midday": 51.130399038765574,
      "prev_midday_price": 974.8599853515625,
      "price_change_pct": 0.8883362031281286,
      "macdv_daily": -11.16,
      "macdv_daily_trend": "Neutral",
      "macdv_delta_1d": 1.15,
      "macdv_delta_5d": -5.52,
      "macdv_delta_10d": -5.28,
      "macdv_trend": "\u2198\u2198",
      "macdv_trend_label": "CRASH",
      "days_in_zone": 15,
      "next_threshold": null,
      "next_threshold_distance": null,
      "signal_crossover": null,
      "macdv_decay_accel": 4.68,
      "transition_type": "stable_ranging",
      "transition_score": 0,
      "macdv_zone": null,
      "macdv_zone_display": null,
      "macdv_categorical_percentile": null,
      "macdv_asymmetric_percentile": null,
      "macdv_interpretation": null
    },
    {
      "ticker": "AAPL",
      "name": "Apple",
      "current_date": "2026-03-26 12:00",
      "current_price": 254.08999633789062,
      "current_percentile": 86.05577689243027,
      "percentile_cohort": "extreme_high",
      "zone_label": "85-100th percentile (Extreme High)",
      "in_entry_zone": false,
      "regime": "momentum",
      "is_mean_reverter": false,
      "is_momentum": true,
      "volatility_level": "Medium-High",
      "live_expectancy": {
        "expected_win_rate": 0.5319431039597075,
        "expected_return_pct": 0.027199999999999988,
        "expected_holding_days": 4.0,
        "expected_return_per_day_pct": 0.006799999999999997,
        "risk_adjusted_expectancy_pct": 0.018133333333333324,
        "sample_size": 50
      },
      "data_source": "4h",
      "prev_midday_percentile": 68.65079365079364,
      "change_since_prev_midday": 17.40498324163663,
      "prev_midday_price": 252.6199951171875,
      "price_change_pct": 0.5819021649577693,
      "macdv_daily": -62.19,
      "macdv_daily_trend": "Bearish",
      "macdv_delta_1d": 6.72,
      "macdv_delta_5d": -0.16,
      "macdv_delta_10d": -3.48,
      "macdv_trend": "\u2192",
      "macdv_trend_label": "FLAT",
      "days_in_zone": 7,
      "next_threshold": null,
      "next_threshold_distance": null,
      "signal_crossover": null,
      "macdv_decay_accel": 6.36,
      "transition_type": "bearish_exhaustion",
      "transition_score": 46,
      "macdv_zone": "ranging",
      "macdv_zone_display": "Ranging (-50 to +50)",
      "macdv_categorical_percentile": 38.0,
      "macdv_asymmetric_percentile": 50.0,
      "macdv_interpretation": "\u27a1\ufe0f Mid-range - within Range"
    }
  ],
  "summary": {
    "total_tickers": 32,
    "in_entry_zone": 6,
    "extreme_low_opportunities": 1,
    "low_opportunities": 5
  },
  "prev_midday_snapshot": {
    "market_date": "2026-03-25",
    "captured_at": "2026-03-25T16:00:00 (close, computed)",
    "timeframe": "4h",
    "from_fallback": true
  }
}
